{
	"versao": {
		"DataHora":"2018/11/10 19:30",
		"ID":"1.3",
		"OBS":"Atualizando pontos, inserindo o valor Ruas."
	},

	"pontos": [
		{"PontoID":"Ponto 1","Latitude":"-26.17371","Longitude":"-50.39008","SentidoPonto":"Bairro","Comentario":"Praça Lauro Mueller","Rua":"Praça Lauro Mueller"},
		{"PontoID":"Ponto 2","Latitude":"-26.17314","Longitude":"-50.38816","SentidoPonto":"Bairro","Comentario":"Ponto virtual","Rua":"R. Fracisco de Paula Pereira"},
		{"PontoID":"Ponto 3","Latitude":"-26.17154","Longitude":"-50.38456","SentidoPonto":"Bairro","Comentario":"Ponto virtual","Rua":"V. Guilherme Prust"},
		{"PontoID":"Ponto 4","Latitude":"-26.1735","Longitude":"-50.37932","SentidoPonto":"Bairro","Comentario":"Ponto virtual","Rua":"Av. Expedicionários "},
		{"PontoID":"Ponto 5","Latitude":"-26.17628","Longitude":"-50.37574","SentidoPonto":"Bairro","Comentario":"Ponto virtual","Rua":"Av. Expedicionários "},
		{"PontoID":"Ponto 6","Latitude":"-26.18053","Longitude":"-50.37033","SentidoPonto":"Bairro","Comentario":"Ponto virtual","Rua":"Av. Expedicionários "},
		{"PontoID":"Ponto 7","Latitude":"-26.18301","Longitude":"-50.3672","SentidoPonto":"Bairro","Comentario":"IFSC","Rua":"Av. Expedicionários "},
		{"PontoID":"Ponto 8","Latitude":"-26.18411","Longitude":"-50.36288","SentidoPonto":"Bairro","Comentario":"Ponto virtual","Rua":"R. Alvino Voigt"},
		{"PontoID":"Ponto 9","Latitude":"-26.18573","Longitude":"-50.36077","SentidoPonto":"Bairro","Comentario":"Ponto virtual","Rua":"R. Alvino Voigt"},
		{"PontoID":"Ponto 10","Latitude":"-26.18674","Longitude":"-50.36037","SentidoPonto":"Bairro","Comentario":"Ponto virtual","Rua":"R. Jacobe Scheuer"},
		{"PontoID":"Ponto 11","Latitude":"-26.18796","Longitude":"-50.36464","SentidoPonto":"Bairro","Comentario":"Ponto virtual","Rua":"Lateral SC280"},
		{"PontoID":"Ponto 12","Latitude":"-26.18869","Longitude":"-50.36881","SentidoPonto":"Bairro","Comentario":"Ponto virtual","Rua":"Lateral SC280"},
		{"PontoID":"Ponto 13","Latitude":"-26.18942","Longitude":"-50.37346","SentidoPonto":"Bairro","Comentario":"Ponto virtual. Próx. retifica Motocar","Rua":"Lateral SC280"},
		{"PontoID":"Ponto 14","Latitude":"-26.1907","Longitude":"-50.37833","SentidoPonto":"Bairro","Comentario":"Ponto virtual","Rua":"R. Mario Maier"},
		{"PontoID":"Ponto 15","Latitude":"-26.19408","Longitude":"-50.378","SentidoPonto":"Bairro","Comentario":"Ponto virtual","Rua":"R. Jacobe Fuck"},
		{"PontoID":"Ponto 16","Latitude":"-26.19588","Longitude":"-50.37824","SentidoPonto":"Bairro","Comentario":"Ponto virtual","Rua":"R. Sergio Gapski"},
		{"PontoID":"Ponto 17","Latitude":"-26.19959","Longitude":"-50.37876","SentidoPonto":"Bairro","Comentario":"Ponto virtual","Rua":"(Sem nome)"},
		{"PontoID":"Ponto 18","Latitude":"-26.20107","Longitude":"-50.38282","SentidoPonto":"Bairro","Comentario":"Ponto virtual","Rua":"(Sem nome)"},
		{"PontoID":"Ponto 19","Latitude":"-26.203022","Longitude":"-50.384556","SentidoPonto":"Bairro","Comentario":"Ponto Físico","Rua":"(Sem nome)"},
		{"PontoID":"Ponto 20","Latitude":"-26.205336","Longitude":"-50.383465","SentidoPonto":"Bairro","Comentario":"Ponto Físico","Rua":"(Sem nome)"},
		{"PontoID":"Ponto 21","Latitude":"-26.20448","Longitude":"-50.37991","SentidoPonto":"Bairro","Comentario":"Ponto virtual","Rua":"R. Antonio Grosskopf"},
		{"PontoID":"Ponto 22","Latitude":"-26.200403","Longitude":"-50.37675","SentidoPonto":"Bairro","Comentario":"Ponto Físico","Rua":"R. Narciso Ruthes"},
		{"PontoID":"Ponto 23","Latitude":"-26.1979","Longitude":"-50.37772","SentidoPonto":"Praça","Comentario":"Ponto virtual","Rua":"R. Sergio Gapski"},
		{"PontoID":"Ponto 24","Latitude":"-26.19376","Longitude":"-50.37713","SentidoPonto":"Praça","Comentario":"Ponto Físico. Próximo da Escola Estadual Emília Ferrero","Rua":"R. Jacobe Fuck"},
		{"PontoID":"Ponto 25","Latitude":"-26.19062","Longitude":"-50.37832","SentidoPonto":"Praça","Comentario":"Ponto virtual","Rua":"R. Mario Maier"},
		{"PontoID":"Ponto 26","Latitude":"-26.18956","Longitude":"-50.37293","SentidoPonto":"Praça","Comentario":"Ponto virtual","Rua":"Lateral SC280"},
		{"PontoID":"Ponto 27","Latitude":"-26.18818","Longitude":"-50.36438","SentidoPonto":"Praça","Comentario":"Ponto virtual, próximo ao Procopiak","Rua":"Lateral SC280"},
		{"PontoID":"Ponto 28","Latitude":"-26.18422","Longitude":"-50.36262","SentidoPonto":"Praça","Comentario":"Ponto Físico","Rua":"R. Alvino Voigt"},
		{"PontoID":"Ponto 29","Latitude":"-26.18318","Longitude":"-50.36685","SentidoPonto":"Praça","Comentario":"Ponto Físico","Rua":"Av. Expedicionários "},
		{"PontoID":"Ponto 30","Latitude":"-26.181576","Longitude":"-50.36902","SentidoPonto":"Praça","Comentario":"Ponto Físico","Rua":"Av. Expedicionários "},
		{"PontoID":"Ponto 31","Latitude":"-26.179176","Longitude":"-50.371998","SentidoPonto":"Praça","Comentario":"Ponto Físico","Rua":"Av. Expedicionários "},
		{"PontoID":"Ponto 32","Latitude":"-26.176903","Longitude":"-50.37489","SentidoPonto":"Praça","Comentario":"Ponto Físico","Rua":"Av. Expedicionários "},
		{"PontoID":"Ponto 33","Latitude":"-26.173763","Longitude":"-50.378975","SentidoPonto":"Praça","Comentario":"Ponto Físico","Rua":"Av. Expedicionários "},
		{"PontoID":"Ponto 34","Latitude":"-26.17144","Longitude":"-50.38373","SentidoPonto":"Praça","Comentario":"Ponto virtual. Próximo ao posto Guapo.","Rua":"R. Fracisco de Paula Pereira"},
		{"PontoID":"Ponto 35","Latitude":"-26.17224","Longitude":"-50.38723","SentidoPonto":"Praça","Comentario":"Ponto virtual","Rua":"R. Fracisco de Paula Pereira"},
		{"PontoID":"Ponto 36","Latitude":"-26.178017","Longitude":"-50.390713","SentidoPonto":"Bairro","Comentario":"Ponto Físico","Rua":"R. Frei Menandro Kamps"},
		{"PontoID":"Ponto 37","Latitude":"-26.18097","Longitude":"-50.39417","SentidoPonto":"Bairro","Comentario":"Ponto virtual","Rua":"R. Fracisco de Paula Pereira"},
		{"PontoID":"Ponto 38","Latitude":"-26.18696","Longitude":"-50.39986","SentidoPonto":"Bairro","Comentario":"Ponto virtual","Rua":"R. Major Vieira"},
		{"PontoID":"Ponto 39","Latitude":"-26.18795","Longitude":"-50.40136","SentidoPonto":"Bairro","Comentario":"Ponto virtual","Rua":"R. Cidade de Jaú"},
		{"PontoID":"Ponto 40","Latitude":"-26.18752","Longitude":"-50.4067","SentidoPonto":"Bairro","Comentario":"Ponto virtual","Rua":"Estrada Dona Francisca "},
		{"PontoID":"Ponto 41","Latitude":"-26.18864","Longitude":"-50.4093","SentidoPonto":"Bairro","Comentario":"Ponto virtual","Rua":"Estrada Dona Francisca "},
		{"PontoID":"Ponto 42","Latitude":"-26.18945","Longitude":"-50.41333","SentidoPonto":"Bairro","Comentario":"Ponto virtual","Rua":"Estrada Dona Francisca "},
		{"PontoID":"Ponto 43","Latitude":"-26.19322","Longitude":"-50.41748","SentidoPonto":"Bairro","Comentario":"Ponto virtual","Rua":"Estrada Dona Francisca "},
		{"PontoID":"Ponto 44","Latitude":"-26.20461","Longitude":"-50.42157","SentidoPonto":"Bairro","Comentario":"Ponto virtual","Rua":"Estrada Dona Francisca "},
		{"PontoID":"Ponto 45","Latitude":"-26.20312","Longitude":"-50.42121","SentidoPonto":"Bairro","Comentario":"Ponto virtual","Rua":"Estrada Dona Francisca "},
		{"PontoID":"Ponto 46","Latitude":"-26.19434","Longitude":"-50.41965","SentidoPonto":"Bairro","Comentario":"Ponto virtual","Rua":"Estrada Dona Francisca "},
		{"PontoID":"Ponto 47","Latitude":"-26.19323","Longitude":"-50.41729","SentidoPonto":"Bairro","Comentario":"Ponto virtual","Rua":"Estrada Dona Francisca "},
		{"PontoID":"Ponto 48","Latitude":"-26.1887","Longitude":"-50.4092","SentidoPonto":"Bairro","Comentario":"Ponto virtual","Rua":"Estrada Dona Francisca "},
		{"PontoID":"Ponto 49","Latitude":"-26.18757","Longitude":"-50.40652","SentidoPonto":"Bairro","Comentario":"Ponto virtual","Rua":"Estrada Dona Francisca "},
		{"PontoID":"Ponto 50","Latitude":"-26.18809","Longitude":"-50.40135","SentidoPonto":"Bairro","Comentario":"Ponto virtual","Rua":"R. Cidade de Jaú"},
		{"PontoID":"Ponto 51","Latitude":"-26.18695","Longitude":"-50.39977","SentidoPonto":"Bairro","Comentario":"Ponto virtual","Rua":"R. Maj. Vieira"},
		{"PontoID":"Ponto 52","Latitude":"-26.1803","Longitude":"-50.39352","SentidoPonto":"Bairro","Comentario":"Ponto virtual","Rua":"R. Francisco de Paula Pereira"},
		{"PontoID":"Ponto 53","Latitude":"-26.177446","Longitude":"-50.391396","SentidoPonto":"Bairro","Comentario":"Ponto virtual","Rua":"R. Francisco de Paula Pereira"},
		{"PontoID":"Ponto 54","Latitude":"-26.17319","Longitude":"-50.38978","SentidoPonto":"Bairro","Comentario":"Ponto virtual","Rua":"R. Eugênio de Souza"},
		{"PontoID":"Ponto 55","Latitude":"-26.17256","Longitude":"-50.39073","SentidoPonto":"Bairro","Comentario":"Ponto virtual","Rua":"R. Eugênio de Souza"},
		{"PontoID":"Ponto 56","Latitude":"-26.17127","Longitude":"-50.39427","SentidoPonto":"Bairro","Comentario":"Ponto virtual","Rua":"R. Roberto Eike"},
		{"PontoID":"Ponto 57","Latitude":"-26.16886","Longitude":"-50.39954","SentidoPonto":"Bairro","Comentario":"Ponto virtual","Rua":"R. Otto Friedrich"},
		{"PontoID":"Ponto 58","Latitude":"-26.166733","Longitude":"-50.399006","SentidoPonto":"Bairro","Comentario":"Ponto virtual","Rua":"R. Otto Friedrich"},
		{"PontoID":"Ponto 59","Latitude":"-26.16394","Longitude":"-50.40175","SentidoPonto":"Bairro","Comentario":"Ponto virtual","Rua":"R. Feres João Isphair"},
		{"PontoID":"Ponto 60","Latitude":"-26.16331","Longitude":"-50.4047","SentidoPonto":"Bairro","Comentario":"Ponto virtual","Rua":"R. Feres João Isphair"},
		{"PontoID":"Ponto 61","Latitude":"-26.16287","Longitude":"-50.40664","SentidoPonto":"Bairro","Comentario":"Ponto virtual","Rua":"R. Feres João Isphair"},
		{"PontoID":"Ponto 62","Latitude":"-26.16472","Longitude":"-50.40729","SentidoPonto":"Bairro","Comentario":"Ponto virtual","Rua":"Rua Henrique Sorg"},
		{"PontoID":"Ponto 63","Latitude":"-26.16797","Longitude":"-50.40774","SentidoPonto":"Bairro","Comentario":"Ponto virtual","Rua":"Av. Sen. Ivo D'Aquino"},
		{"PontoID":"Ponto 64","Latitude":"-26.16886","Longitude":"-50.40467","SentidoPonto":"Bairro","Comentario":"Ponto virtual","Rua":"R. Roberto Eike"},
		{"PontoID":"Ponto 65","Latitude":"-26.16996","Longitude":"-50.40037","SentidoPonto":"Bairro","Comentario":"Ponto virtual","Rua":"R. Roberto Eike"},
		{"PontoID":"Ponto 66","Latitude":"-26.17062","Longitude":"-50.39736","SentidoPonto":"Bairro","Comentario":"Ponto virtual","Rua":"R. Roberto Eike"},
		{"PontoID":"Ponto 67","Latitude":"-26.17284","Longitude":"-50.39413","SentidoPonto":"Bairro","Comentario":"Ponto virtual","Rua":"R. Getúlio Vargas"},
		{"PontoID":"Ponto 68","Latitude":"-26.17718","Longitude":"-50.39488","SentidoPonto":"Bairro","Comentario":"Ponto virtual","Rua":"R. Cel. Albuquerque"},
		{"PontoID":"Ponto 69","Latitude":"-26.18222","Longitude":"-50.39888","SentidoPonto":"Bairro","Comentario":"Ponto virtual","Rua":"R. Duque de Caxias"},
		{"PontoID":"Ponto 70","Latitude":"-26.18358","Longitude":"-50.40079","SentidoPonto":"Bairro","Comentario":"Ponto virtual","Rua":"R. Duque de Caxias"},
		{"PontoID":"Ponto 71","Latitude":"-26.18143","Longitude":"-50.40276","SentidoPonto":"Bairro","Comentario":"Ponto virtual","Rua":"R. Lourenço Wrublevski"},
		{"PontoID":"Ponto 72","Latitude":"-26.17497","Longitude":"-50.40569","SentidoPonto":"Bairro","Comentario":"Ponto virtual","Rua":"R. Álvaro Soares Machado"},
		{"PontoID":"Ponto 73","Latitude":"-26.17408","Longitude":"-50.41035","SentidoPonto":"Bairro","Comentario":"Ponto virtual","Rua":"R. Álvaro Soares Machado"},
		{"PontoID":"Ponto 74","Latitude":"-26.1723","Longitude":"-50.41196","SentidoPonto":"Bairro","Comentario":"Ponto virtual","Rua":"R. Reuneau Cubas"},
		{"PontoID":"Ponto 75","Latitude":"-26.16656","Longitude":"-50.41703","SentidoPonto":"Bairro","Comentario":"Ponto virtual","Rua":"R. Sen. Ivo Dáquino"},
		{"PontoID":"Ponto 76","Latitude":"-26.16691","Longitude":"-50.42194","SentidoPonto":"Bairro","Comentario":"Ponto virtual","Rua":"R. Sen. Ivo Dáquino"},
		{"PontoID":"Ponto 77","Latitude":"-26.16638","Longitude":"-50.42631","SentidoPonto":"Bairro","Comentario":"Ponto virtual","Rua":"R. Oto Kohler"},
		{"PontoID":"Ponto 78","Latitude":"-26.16744","Longitude":"-50.4272","SentidoPonto":"Bairro","Comentario":"Ponto virtual","Rua":"R. Sen. Ivo Dáquino"},
		{"PontoID":"Ponto 79","Latitude":"-26.16728","Longitude":"-50.4251","SentidoPonto":"Bairro","Comentario":"Ponto virtual","Rua":"R. Sen. Ivo Dáquino"},
		{"PontoID":"Ponto 80","Latitude":"-26.16664","Longitude":"-50.41724","SentidoPonto":"Bairro","Comentario":"Ponto virtual","Rua":"R. Sen. Ivo Dáquino"},
		{"PontoID":"Ponto 81","Latitude":"-26.16677","Longitude":"-50.41497","SentidoPonto":"Bairro","Comentario":"Ponto virtual","Rua":"R. Sen. Ivo Dáquino"},
		{"PontoID":"Ponto 82","Latitude":"-26.16718","Longitude":"-50.41188","SentidoPonto":"Bairro","Comentario":"Ponto virtual","Rua":"R. Sen. Ivo Dáquino"},
		{"PontoID":"Ponto 63","Latitude":"-26.16797","Longitude":"-50.40774","SentidoPonto":"Bairro","Comentario":"Ponto virtual","Rua":"Av. Sen. Ivo D'Aquino"},
		{"PontoID":"Ponto 64","Latitude":"-26.16886","Longitude":"-50.40467","SentidoPonto":"Bairro","Comentario":"Ponto virtual","Rua":"R. Roberto Eike"},
		{"PontoID":"Ponto 83","Latitude":"-26.16968","Longitude":"-50.40172","SentidoPonto":"Bairro","Comentario":"","Rua":"R. Roberto Eike"},
		{"PontoID":"Ponto 66","Latitude":"-26.17062","Longitude":"-50.39736","SentidoPonto":"Bairro","Comentario":"Ponto virtual","Rua":"R. Roberto Eike"},
		{"PontoID":"Ponto 67","Latitude":"-26.17284","Longitude":"-50.39413","SentidoPonto":"Bairro","Comentario":"Ponto virtual","Rua":"R. Getúlio Vargas"},
		{"PontoID":"Ponto 1","Latitude":"-26.17371","Longitude":"-50.39008","SentidoPonto":"Bairro","Comentario":"Praça Lauro Mueller","Rua":"Praça Lauro Mueller"},
		{"PontoID":"Ponto 1","Latitude":"-26.17371","Longitude":"-50.39008","SentidoPonto":"Bairro","Comentario":"Praça Lauro Mueller","Rua":"Praça Lauro Mueller"},
		{"PontoID":"Ponto 86","Latitude":"-26.182","Longitude":"-50.38656","SentidoPonto":"Bairro","Comentario":"n/a","Rua":"R. Caetano Costa"},
		{"PontoID":"Ponto 87","Latitude":"-26.18387","Longitude":"-50.38346","SentidoPonto":"Bairro","Comentario":"n/a","Rua":"R. Caetano Costa"},
		{"PontoID":"Ponto 88","Latitude":"-26.18675","Longitude":"-50.37938","SentidoPonto":"Bairro","Comentario":"n/a","Rua":"Av. Rubens Ribeiro da Silva"},
		{"PontoID":"Ponto 89","Latitude":"-26.1891","Longitude":"-50.37639","SentidoPonto":"Bairro","Comentario":"n/a","Rua":"Av. Rubens Ribeiro da Silva"},
		{"PontoID":"Ponto 90","Latitude":"-26.19218","Longitude":"-50.37234","SentidoPonto":"Bairro","Comentario":"n/a","Rua":"SC-477"},
		{"PontoID":"Ponto 91","Latitude":"-26.19504","Longitude":"-50.36948","SentidoPonto":"Bairro","Comentario":"n/a","Rua":"R. Loacir Muniz"},
		{"PontoID":"Ponto 92","Latitude":"-26.19685","Longitude":"-50.37029","SentidoPonto":"Bairro","Comentario":"n/a","Rua":"R. Casemiro Kwicien"},
		{"PontoID":"Ponto 93","Latitude":"-26.19345","Longitude":"-50.37065","SentidoPonto":"Bairro","Comentario":"n/a","Rua":"SC-477"},
		{"PontoID":"Ponto 94","Latitude":"-26.19066","Longitude":"-50.37415","SentidoPonto":"Bairro","Comentario":"n/a","Rua":"SC-477"},
		{"PontoID":"Ponto 95","Latitude":"-26.18789","Longitude":"-50.37771","SentidoPonto":"Bairro","Comentario":"n/a","Rua":"Av. Rubens Ribeiro da Silva"},
		{"PontoID":"Ponto 96","Latitude":"-26.18519","Longitude":"-50.37716","SentidoPonto":"Bairro","Comentario":"n/a","Rua":"R. Nazir Cordeiro"},
		{"PontoID":"Ponto 97","Latitude":"-26.17964","Longitude":"-50.37726","SentidoPonto":"Bairro","Comentario":"n/a","Rua":"R. Bento de Lima"},
		{"PontoID":"Ponto 98","Latitude":"-26.17791","Longitude":"-50.37966","SentidoPonto":"Bairro","Comentario":"n/a","Rua":"R. Adolfo Bading"},
		{"PontoID":"Ponto 99","Latitude":"-26.18085","Longitude":"-50.3845","SentidoPonto":"Bairro","Comentario":"n/a","Rua":"R. Paul Harris"},
		{"PontoID":"Ponto 100","Latitude":"-26.18093","Longitude":"-50.38807","SentidoPonto":"Bairro","Comentario":"n/a","Rua":"R. Caetano Costa"}
	],

	"linhas":[
		{"LinhaID":"Aparecida",
			"RoteiroInicio":"Terminal urbano",
			"RoteiroFim":"Bairro Aparecida",
			"RoteiroPontos":"Ponto 1, Ponto 36, Ponto 37, Ponto 38, Ponto 39, Ponto 40, Ponto 41, Ponto 42, Ponto 43, Ponto 44, Ponto 45, Ponto 46, Ponto 47, Ponto 48, Ponto 49, Ponto 50, Ponto 51, Ponto 52, Ponto 53, Ponto 54, Ponto 55, Ponto 56, Ponto 57, Ponto 58, Ponto 59, Ponto 60, Ponto 61, Ponto 62, Ponto 63, Ponto 64, Ponto 65, Ponto 66, Ponto 67"
		},
		{"LinhaID":"Cohab I, II",
			"RoteiroInicio":"Terminal Urbano",
			"RoteiroFim":"Bairro Cohab II",
			"RoteiroPontos":"Ponto 1, Ponto 68, Ponto 69, Ponto 70, Ponto 71, Ponto 72, Ponto 73, Ponto 74, Ponto 75, Ponto 76, Ponto 77, Ponto 78, Ponto 79, Ponto 80, Ponto 81, Ponto 82, Ponto 64, Ponto 83, Ponto 84, Ponto 36, Ponto 85, Ponto 86, Ponto 87, Ponto 88, Ponto 89, Ponto 90, Ponto 91, Ponto 92, Ponto 93, Ponto 94, Ponto 95, Ponto 96, Ponto 97, Ponto 98, Ponto 99, Ponto 100, Ponto 53, Ponto 1"
		},
		{"LinhaID":"Campo Água Verde",
			"RoteiroPontos":"Ponto 1, Ponto 2, Ponto 3, Ponto 4, Ponto 5, Ponto 6, Ponto 7, Ponto 8, Ponto 9, Ponto 10, Ponto 11, Ponto 12, Ponto 13, Ponto 14, Ponto 15, Ponto 16, Ponto 17, Ponto 18, Ponto 19, Ponto 20, Ponto 21, Ponto 22, Ponto 23, Ponto 24, Ponto 25, Ponto 26, Ponto 27, Ponto 28, Ponto 29, Ponto 30, Ponto 31, Ponto 32, Ponto 33, Ponto 34, Ponto 35",
			"RoteiroInicio":"Terminal Urbano",
			"RoteiroFim":"Bairro Cohab II, Centro, ETC"
		}
	],

	"horaLinha":[
		{"LinhaID":"Cohab I, II","RoteiroInicio":"Terminal Urbano","RoteiroFim":"Bairro Cohab I","DiaSemana":"2, 3, 4, 5, 6","Hora":"06:05"},
		{"LinhaID":"Cohab I, II","RoteiroInicio":"Terminal Urbano","RoteiroFim":"Bairro Cohab I","DiaSemana":"2, 3, 4, 5, 6","Hora":"07:05"},
		{"LinhaID":"Cohab I, II","RoteiroInicio":"Terminal Urbano","RoteiroFim":"Bairro Cohab I","DiaSemana":"2, 3, 4, 5, 6","Hora":"08:05"},
		{"LinhaID":"Cohab I, II","RoteiroInicio":"Terminal Urbano","RoteiroFim":"Bairro Cohab I","DiaSemana":"2, 3, 4, 5, 6","Hora":"09:05"},
		{"LinhaID":"Cohab I, II","RoteiroInicio":"Terminal Urbano","RoteiroFim":"Bairro Cohab I","DiaSemana":"2, 3, 4, 5, 6","Hora":"10:05"},
		{"LinhaID":"Cohab I, II","RoteiroInicio":"Terminal Urbano","RoteiroFim":"Bairro Cohab I","DiaSemana":"2, 3, 4, 5, 6","Hora":"11:05"},
		{"LinhaID":"Cohab I, II","RoteiroInicio":"Terminal Urbano","RoteiroFim":"Bairro Cohab I","DiaSemana":"2, 3, 4, 5, 6","Hora":"12:05"},
		{"LinhaID":"Cohab I, II","RoteiroInicio":"Terminal Urbano","RoteiroFim":"Bairro Cohab I","DiaSemana":"2, 3, 4, 5, 6","Hora":"13:05"},
		{"LinhaID":"Cohab I, II","RoteiroInicio":"Terminal Urbano","RoteiroFim":"Bairro Cohab I","DiaSemana":"2, 3, 4, 5, 6","Hora":"14:05"},
		{"LinhaID":"Cohab I, II","RoteiroInicio":"Terminal Urbano","RoteiroFim":"Bairro Cohab I","DiaSemana":"2, 3, 4, 5, 6","Hora":"15:05"},
		{"LinhaID":"Cohab I, II","RoteiroInicio":"Terminal Urbano","RoteiroFim":"Bairro Cohab I","DiaSemana":"2, 3, 4, 5, 6","Hora":"16:05"},
		{"LinhaID":"Cohab I, II","RoteiroInicio":"Terminal Urbano","RoteiroFim":"Bairro Cohab I","DiaSemana":"2, 3, 4, 5, 6","Hora":"17:05"},
		{"LinhaID":"Cohab I, II","RoteiroInicio":"Terminal Urbano","RoteiroFim":"Bairro Cohab I","DiaSemana":"2, 3, 4, 5, 6","Hora":"18:05"},
		{"LinhaID":"Cohab I, II","RoteiroInicio":"Terminal Urbano","RoteiroFim":"Bairro Cohab I","DiaSemana":"2, 3, 4, 5, 6","Hora":"19:05"},
		{"LinhaID":"Cohab I, II","RoteiroInicio":"Terminal Urbano","RoteiroFim":"Bairro Cohab I","DiaSemana":"7","Hora":"06:05"},
		{"LinhaID":"Cohab I, II","RoteiroInicio":"Terminal Urbano","RoteiroFim":"Bairro Cohab I","DiaSemana":"7","Hora":"07:05"},
		{"LinhaID":"Cohab I, II","RoteiroInicio":"Terminal Urbano","RoteiroFim":"Bairro Cohab I","DiaSemana":"7","Hora":"08:05"},
		{"LinhaID":"Cohab I, II","RoteiroInicio":"Terminal Urbano","RoteiroFim":"Bairro Cohab I","DiaSemana":"7","Hora":"09:05"},
		{"LinhaID":"Cohab I, II","RoteiroInicio":"Terminal Urbano","RoteiroFim":"Bairro Cohab I","DiaSemana":"7","Hora":"10:05"},
		{"LinhaID":"Cohab I, II","RoteiroInicio":"Terminal Urbano","RoteiroFim":"Bairro Cohab I","DiaSemana":"7","Hora":"11:05"},
		{"LinhaID":"Cohab I, II","RoteiroInicio":"Terminal Urbano","RoteiroFim":"Bairro Cohab I","DiaSemana":"7","Hora":"12:05"},
		{"LinhaID":"Cohab I, II","RoteiroInicio":"Terminal Urbano","RoteiroFim":"Bairro Cohab I","DiaSemana":"7","Hora":"13:05"},
		{"LinhaID":"Cohab I, II","RoteiroInicio":"Terminal Urbano","RoteiroFim":"Bairro Cohab I","DiaSemana":"7","Hora":"14:05"},
		{"LinhaID":"Cohab I, II","RoteiroInicio":"Terminal Urbano","RoteiroFim":"Bairro Cohab I","DiaSemana":"7","Hora":"15:05"},
		{"LinhaID":"Cohab I, II","RoteiroInicio":"Terminal Urbano","RoteiroFim":"Bairro Cohab I","DiaSemana":"7","Hora":"16:05"},
		{"LinhaID":"Cohab I, II","RoteiroInicio":"Terminal Urbano","RoteiroFim":"Bairro Cohab I","DiaSemana":"7","Hora":"17:05"},
		{"LinhaID":"Cohab I, II","RoteiroInicio":"Terminal Urbano","RoteiroFim":"Bairro Cohab I","DiaSemana":"7","Hora":"18:05"},
		{"LinhaID":"Cohab I, II","RoteiroInicio":"Terminal Urbano","RoteiroFim":"Bairro Cohab I","DiaSemana":"1, 0","Hora":"09:00"},
		{"LinhaID":"Cohab I, II","RoteiroInicio":"Terminal Urbano","RoteiroFim":"Bairro Cohab I","DiaSemana":"1, 0","Hora":"10:00"},
		{"LinhaID":"Cohab I, II","RoteiroInicio":"Terminal Urbano","RoteiroFim":"Bairro Cohab I","DiaSemana":"1, 0","Hora":"15:00"},
		{"LinhaID":"Cohab I, II","RoteiroInicio":"Terminal Urbano","RoteiroFim":"Bairro Cohab I","DiaSemana":"1, 0","Hora":"16:00"},
		{"LinhaID":"Cohab I, II","RoteiroInicio":"Terminal Urbano","RoteiroFim":"Bairro Cohab I","DiaSemana":"1, 0","Hora":"17:00"},
		{"LinhaID":"Campo Água Verde","RoteiroInicio":"Terminal Urbano","RoteiroFim":"Bairro Campo Água Verde","DiaSemana":"2, 3, 4, 5, 6","Hora":"06:05"},
		{"LinhaID":"Campo Água Verde","RoteiroInicio":"Terminal Urbano","RoteiroFim":"Bairro Campo Água Verde","DiaSemana":"2, 3, 4, 5, 6","Hora":"07:05"},
		{"LinhaID":"Campo Água Verde","RoteiroInicio":"Terminal Urbano","RoteiroFim":"Bairro Campo Água Verde","DiaSemana":"2, 3, 4, 5, 6","Hora":"08:05"},
		{"LinhaID":"Campo Água Verde","RoteiroInicio":"Terminal Urbano","RoteiroFim":"Bairro Campo Água Verde","DiaSemana":"2, 3, 4, 5, 6","Hora":"09:05"},
		{"LinhaID":"Campo Água Verde","RoteiroInicio":"Terminal Urbano","RoteiroFim":"Bairro Campo Água Verde","DiaSemana":"2, 3, 4, 5, 6","Hora":"10:05"},
		{"LinhaID":"Campo Água Verde","RoteiroInicio":"Terminal Urbano","RoteiroFim":"Bairro Campo Água Verde","DiaSemana":"2, 3, 4, 5, 6","Hora":"11:05"},
		{"LinhaID":"Campo Água Verde","RoteiroInicio":"Terminal Urbano","RoteiroFim":"Bairro Campo Água Verde","DiaSemana":"2, 3, 4, 5, 6","Hora":"12:05"},
		{"LinhaID":"Campo Água Verde","RoteiroInicio":"Terminal Urbano","RoteiroFim":"Bairro Campo Água Verde","DiaSemana":"2, 3, 4, 5, 6","Hora":"13:05"},
		{"LinhaID":"Campo Água Verde","RoteiroInicio":"Terminal Urbano","RoteiroFim":"Bairro Campo Água Verde","DiaSemana":"2, 3, 4, 5, 6","Hora":"14:05"},
		{"LinhaID":"Campo Água Verde","RoteiroInicio":"Terminal Urbano","RoteiroFim":"Bairro Campo Água Verde","DiaSemana":"2, 3, 4, 5, 6","Hora":"15:05"},
		{"LinhaID":"Campo Água Verde","RoteiroInicio":"Terminal Urbano","RoteiroFim":"Bairro Campo Água Verde","DiaSemana":"2, 3, 4, 5, 6","Hora":"16:05"},
		{"LinhaID":"Campo Água Verde","RoteiroInicio":"Terminal Urbano","RoteiroFim":"Bairro Campo Água Verde","DiaSemana":"2, 3, 4, 5, 6","Hora":"17:05"},
		{"LinhaID":"Campo Água Verde","RoteiroInicio":"Terminal Urbano","RoteiroFim":"Bairro Campo Água Verde","DiaSemana":"2, 3, 4, 5, 6","Hora":"18:05"},
		{"LinhaID":"Campo Água Verde","RoteiroInicio":"Terminal Urbano","RoteiroFim":"Bairro Campo Água Verde","DiaSemana":"2, 3, 4, 5, 6","Hora":"19:05"},
		{"LinhaID":"Campo Água Verde","RoteiroInicio":"Bairro Campo Água Verde","RoteiroFim":"Terminal Urbano","DiaSemana":"2, 3, 4, 5, 6","Hora":"06:35"},
		{"LinhaID":"Campo Água Verde","RoteiroInicio":"Bairro Campo Água Verde","RoteiroFim":"Terminal Urbano","DiaSemana":"2, 3, 4, 5, 6","Hora":"07:35"},
		{"LinhaID":"Campo Água Verde","RoteiroInicio":"Bairro Campo Água Verde","RoteiroFim":"Terminal Urbano","DiaSemana":"2, 3, 4, 5, 6","Hora":"08:35"},
		{"LinhaID":"Campo Água Verde","RoteiroInicio":"Bairro Campo Água Verde","RoteiroFim":"Terminal Urbano","DiaSemana":"2, 3, 4, 5, 6","Hora":"09:35"},
		{"LinhaID":"Campo Água Verde","RoteiroInicio":"Bairro Campo Água Verde","RoteiroFim":"Terminal Urbano","DiaSemana":"2, 3, 4, 5, 6","Hora":"10:35"},
		{"LinhaID":"Campo Água Verde","RoteiroInicio":"Bairro Campo Água Verde","RoteiroFim":"Terminal Urbano","DiaSemana":"2, 3, 4, 5, 6","Hora":"11:35"},
		{"LinhaID":"Campo Água Verde","RoteiroInicio":"Bairro Campo Água Verde","RoteiroFim":"Terminal Urbano","DiaSemana":"2, 3, 4, 5, 6","Hora":"12:35"},
		{"LinhaID":"Campo Água Verde","RoteiroInicio":"Bairro Campo Água Verde","RoteiroFim":"Terminal Urbano","DiaSemana":"2, 3, 4, 5, 6","Hora":"13:35"},
		{"LinhaID":"Campo Água Verde","RoteiroInicio":"Bairro Campo Água Verde","RoteiroFim":"Terminal Urbano","DiaSemana":"2, 3, 4, 5, 6","Hora":"14:35"},
		{"LinhaID":"Campo Água Verde","RoteiroInicio":"Bairro Campo Água Verde","RoteiroFim":"Terminal Urbano","DiaSemana":"2, 3, 4, 5, 6","Hora":"15:35"},
		{"LinhaID":"Campo Água Verde","RoteiroInicio":"Bairro Campo Água Verde","RoteiroFim":"Terminal Urbano","DiaSemana":"2, 3, 4, 5, 6","Hora":"16:35"},
		{"LinhaID":"Campo Água Verde","RoteiroInicio":"Bairro Campo Água Verde","RoteiroFim":"Terminal Urbano","DiaSemana":"2, 3, 4, 5, 6","Hora":"17:35"},
		{"LinhaID":"Campo Água Verde","RoteiroInicio":"Bairro Campo Água Verde","RoteiroFim":"Terminal Urbano","DiaSemana":"2, 3, 4, 5, 6","Hora":"18:35"},
		{"LinhaID":"Campo Água Verde","RoteiroInicio":"Bairro Campo Água Verde","RoteiroFim":"Terminal Urbano","DiaSemana":"2, 3, 4, 5, 6","Hora":"19:35"},
		{"LinhaID":"Campo Água Verde","RoteiroInicio":"Terminal Urbano","RoteiroFim":"Bairro Campo Água Verde","DiaSemana":"7","Hora":"06:05"},
		{"LinhaID":"Campo Água Verde","RoteiroInicio":"Terminal Urbano","RoteiroFim":"Bairro Campo Água Verde","DiaSemana":"7","Hora":"07:05"},
		{"LinhaID":"Campo Água Verde","RoteiroInicio":"Terminal Urbano","RoteiroFim":"Bairro Campo Água Verde","DiaSemana":"7","Hora":"08:05"},
		{"LinhaID":"Campo Água Verde","RoteiroInicio":"Terminal Urbano","RoteiroFim":"Bairro Campo Água Verde","DiaSemana":"7","Hora":"09:05"},
		{"LinhaID":"Campo Água Verde","RoteiroInicio":"Terminal Urbano","RoteiroFim":"Bairro Campo Água Verde","DiaSemana":"7","Hora":"10:05"},
		{"LinhaID":"Campo Água Verde","RoteiroInicio":"Terminal Urbano","RoteiroFim":"Bairro Campo Água Verde","DiaSemana":"7","Hora":"11:05"},
		{"LinhaID":"Campo Água Verde","RoteiroInicio":"Terminal Urbano","RoteiroFim":"Bairro Campo Água Verde","DiaSemana":"7","Hora":"12:05"},
		{"LinhaID":"Campo Água Verde","RoteiroInicio":"Terminal Urbano","RoteiroFim":"Bairro Campo Água Verde","DiaSemana":"7","Hora":"13:05"},
		{"LinhaID":"Campo Água Verde","RoteiroInicio":"Terminal Urbano","RoteiroFim":"Bairro Campo Água Verde","DiaSemana":"7","Hora":"14:05"},
		{"LinhaID":"Campo Água Verde","RoteiroInicio":"Terminal Urbano","RoteiroFim":"Bairro Campo Água Verde","DiaSemana":"7","Hora":"15:05"},
		{"LinhaID":"Campo Água Verde","RoteiroInicio":"Terminal Urbano","RoteiroFim":"Bairro Campo Água Verde","DiaSemana":"7","Hora":"16:05"},
		{"LinhaID":"Campo Água Verde","RoteiroInicio":"Terminal Urbano","RoteiroFim":"Bairro Campo Água Verde","DiaSemana":"7","Hora":"17:05"},
		{"LinhaID":"Campo Água Verde","RoteiroInicio":"Terminal Urbano","RoteiroFim":"Bairro Campo Água Verde","DiaSemana":"7","Hora":"18:05"},
		{"LinhaID":"Campo Água Verde","RoteiroInicio":"Bairro Campo Água Verde","RoteiroFim":"Terminal Urbano","DiaSemana":"7","Hora":"06:35"},
		{"LinhaID":"Campo Água Verde","RoteiroInicio":"Bairro Campo Água Verde","RoteiroFim":"Terminal Urbano","DiaSemana":"7","Hora":"07:35"},
		{"LinhaID":"Campo Água Verde","RoteiroInicio":"Bairro Campo Água Verde","RoteiroFim":"Terminal Urbano","DiaSemana":"7","Hora":"08:35"},
		{"LinhaID":"Campo Água Verde","RoteiroInicio":"Bairro Campo Água Verde","RoteiroFim":"Terminal Urbano","DiaSemana":"7","Hora":"09:35"},
		{"LinhaID":"Campo Água Verde","RoteiroInicio":"Bairro Campo Água Verde","RoteiroFim":"Terminal Urbano","DiaSemana":"7","Hora":"10:35"},
		{"LinhaID":"Campo Água Verde","RoteiroInicio":"Bairro Campo Água Verde","RoteiroFim":"Terminal Urbano","DiaSemana":"7","Hora":"11:35"},
		{"LinhaID":"Campo Água Verde","RoteiroInicio":"Bairro Campo Água Verde","RoteiroFim":"Terminal Urbano","DiaSemana":"7","Hora":"12:35"},
		{"LinhaID":"Campo Água Verde","RoteiroInicio":"Bairro Campo Água Verde","RoteiroFim":"Terminal Urbano","DiaSemana":"7","Hora":"13:35"},
		{"LinhaID":"Campo Água Verde","RoteiroInicio":"Bairro Campo Água Verde","RoteiroFim":"Terminal Urbano","DiaSemana":"7","Hora":"14:35"},
		{"LinhaID":"Campo Água Verde","RoteiroInicio":"Bairro Campo Água Verde","RoteiroFim":"Terminal Urbano","DiaSemana":"7","Hora":"15:35"},
		{"LinhaID":"Campo Água Verde","RoteiroInicio":"Bairro Campo Água Verde","RoteiroFim":"Terminal Urbano","DiaSemana":"7","Hora":"16:35"},
		{"LinhaID":"Campo Água Verde","RoteiroInicio":"Bairro Campo Água Verde","RoteiroFim":"Terminal Urbano","DiaSemana":"7","Hora":"17:35"},
		{"LinhaID":"Campo Água Verde","RoteiroInicio":"Bairro Campo Água Verde","RoteiroFim":"Terminal Urbano","DiaSemana":"7","Hora":"18:35"},
		{"LinhaID":"Campo Água Verde","RoteiroInicio":"Terminal Urbano","RoteiroFim":"Bairro Campo Água Verde","DiaSemana":"0, 1","Hora":"07:05"},
		{"LinhaID":"Campo Água Verde","RoteiroInicio":"Terminal Urbano","RoteiroFim":"Bairro Campo Água Verde","DiaSemana":"0, 1","Hora":"09:05"},
		{"LinhaID":"Campo Água Verde","RoteiroInicio":"Terminal Urbano","RoteiroFim":"Bairro Campo Água Verde","DiaSemana":"0, 1","Hora":"13:05"},
		{"LinhaID":"Campo Água Verde","RoteiroInicio":"Terminal Urbano","RoteiroFim":"Bairro Campo Água Verde","DiaSemana":"0, 1","Hora":"16:05"},
		{"LinhaID":"Campo Água Verde","RoteiroInicio":"Terminal Urbano","RoteiroFim":"Bairro Campo Água Verde","DiaSemana":"0, 1","Hora":"17:05"},
		{"LinhaID":"Campo Água Verde","RoteiroInicio":"Bairro Campo Água Verde","RoteiroFim":"Terminal Urbano","DiaSemana":"0, 1","Hora":"09:00"},
		{"LinhaID":"Campo Água Verde","RoteiroInicio":"Bairro Campo Água Verde","RoteiroFim":"Terminal Urbano","DiaSemana":"0, 1","Hora":"10:00"},
		{"LinhaID":"Campo Água Verde","RoteiroInicio":"Bairro Campo Água Verde","RoteiroFim":"Terminal Urbano","DiaSemana":"0, 1","Hora":"15:00"},
		{"LinhaID":"Campo Água Verde","RoteiroInicio":"Bairro Campo Água Verde","RoteiroFim":"Terminal Urbano","DiaSemana":"0, 1","Hora":"16:00"},
		{"LinhaID":"Campo Água Verde","RoteiroInicio":"Bairro Campo Água Verde","RoteiroFim":"Terminal Urbano","DiaSemana":"0, 1","Hora":"17:00"},
		{"LinhaID":"Cohab II","RoteiroInicio":"Terminal Urbano","RoteiroFim":"Bairro Cohab II","DiaSemana":"0, 1","Hora":"06:30"},
		{"LinhaID":"Cohab II","RoteiroInicio":"Terminal Urbano","RoteiroFim":"Bairro Cohab II","DiaSemana":"0, 1","Hora":"07:30"},
		{"LinhaID":"Cohab II","RoteiroInicio":"Terminal Urbano","RoteiroFim":"Bairro Cohab II","DiaSemana":"0, 1","Hora":"08:30"},
		{"LinhaID":"Cohab II","RoteiroInicio":"Terminal Urbano","RoteiroFim":"Bairro Cohab II","DiaSemana":"0, 1","Hora":"09:30"},
		{"LinhaID":"Cohab II","RoteiroInicio":"Terminal Urbano","RoteiroFim":"Bairro Cohab II","DiaSemana":"0, 1","Hora":"10:30"},
		{"LinhaID":"Cohab II","RoteiroInicio":"Terminal Urbano","RoteiroFim":"Bairro Cohab II","DiaSemana":"0, 1","Hora":"11:30"},
		{"LinhaID":"Cohab II","RoteiroInicio":"Terminal Urbano","RoteiroFim":"Bairro Cohab II","DiaSemana":"0, 1","Hora":"12:30"},
		{"LinhaID":"Cohab II","RoteiroInicio":"Terminal Urbano","RoteiroFim":"Bairro Cohab II","DiaSemana":"0, 1","Hora":"13:30"},
		{"LinhaID":"Cohab II","RoteiroInicio":"Terminal Urbano","RoteiroFim":"Bairro Cohab II","DiaSemana":"0, 1","Hora":"14:30"},
		{"LinhaID":"Cohab II","RoteiroInicio":"Terminal Urbano","RoteiroFim":"Bairro Cohab II","DiaSemana":"0, 1","Hora":"15:30"},
		{"LinhaID":"Cohab II","RoteiroInicio":"Terminal Urbano","RoteiroFim":"Bairro Cohab II","DiaSemana":"0, 1","Hora":"16:30"},
		{"LinhaID":"Cohab II","RoteiroInicio":"Terminal Urbano","RoteiroFim":"Bairro Cohab II","DiaSemana":"0, 1","Hora":"17:30"},
		{"LinhaID":"Cohab II","RoteiroInicio":"Terminal Urbano","RoteiroFim":"Bairro Cohab II","DiaSemana":"0, 1","Hora":"18:30"},
		{"LinhaID":"Cohab II","RoteiroInicio":"Terminal Urbano","RoteiroFim":"Bairro Cohab II","DiaSemana":"0, 1","Hora":"19:30"},
		{"LinhaID":"Cohab II","RoteiroInicio":"Terminal Urbano","RoteiroFim":"Bairro Cohab II","DiaSemana":"7","Hora":"06:30"},
		{"LinhaID":"Cohab II","RoteiroInicio":"Terminal Urbano","RoteiroFim":"Bairro Cohab II","DiaSemana":"7","Hora":"07:30"},
		{"LinhaID":"Cohab II","RoteiroInicio":"Terminal Urbano","RoteiroFim":"Bairro Cohab II","DiaSemana":"7","Hora":"08:30"},
		{"LinhaID":"Cohab II","RoteiroInicio":"Terminal Urbano","RoteiroFim":"Bairro Cohab II","DiaSemana":"7","Hora":"09:30"},
		{"LinhaID":"Cohab II","RoteiroInicio":"Terminal Urbano","RoteiroFim":"Bairro Cohab II","DiaSemana":"7","Hora":"10:30"},
		{"LinhaID":"Cohab II","RoteiroInicio":"Terminal Urbano","RoteiroFim":"Bairro Cohab II","DiaSemana":"7","Hora":"11:30"},
		{"LinhaID":"Cohab II","RoteiroInicio":"Terminal Urbano","RoteiroFim":"Bairro Cohab II","DiaSemana":"7","Hora":"12:30"},
		{"LinhaID":"Cohab II","RoteiroInicio":"Terminal Urbano","RoteiroFim":"Bairro Cohab II","DiaSemana":"7","Hora":"13:30"},
		{"LinhaID":"Cohab II","RoteiroInicio":"Terminal Urbano","RoteiroFim":"Bairro Cohab II","DiaSemana":"7","Hora":"14:30"},
		{"LinhaID":"Cohab II","RoteiroInicio":"Terminal Urbano","RoteiroFim":"Bairro Cohab II","DiaSemana":"7","Hora":"15:30"},
		{"LinhaID":"Cohab II","RoteiroInicio":"Terminal Urbano","RoteiroFim":"Bairro Cohab II","DiaSemana":"7","Hora":"16:30"},
		{"LinhaID":"Cohab II","RoteiroInicio":"Terminal Urbano","RoteiroFim":"Bairro Cohab II","DiaSemana":"7","Hora":"17:30"},
		{"LinhaID":"Cohab II","RoteiroInicio":"Terminal Urbano","RoteiroFim":"Bairro Cohab II","DiaSemana":"7","Hora":"18:30"},
		{"LinhaID":"Cohab II","RoteiroInicio":"Terminal Urbano","RoteiroFim":"Bairro Cohab II","DiaSemana":"0, 1","Hora":"09:00"},
		{"LinhaID":"Cohab II","RoteiroInicio":"Terminal Urbano","RoteiroFim":"Bairro Cohab II","DiaSemana":"0, 1","Hora":"10:00"},
		{"LinhaID":"Cohab II","RoteiroInicio":"Terminal Urbano","RoteiroFim":"Bairro Cohab II","DiaSemana":"0, 1","Hora":"15:00"},
		{"LinhaID":"Cohab II","RoteiroInicio":"Terminal Urbano","RoteiroFim":"Bairro Cohab II","DiaSemana":"0, 1","Hora":"16:00"},
		{"LinhaID":"Cohab II","RoteiroInicio":"Terminal Urbano","RoteiroFim":"Bairro Cohab II","DiaSemana":"0, 1","Hora":"17:00"}
	],

	"horaLinhaPontos":[
		{"LinhaID":"Campo Água Verde","RoteiroInicio":"Praça","SentidoLinha":"Bairro Água Verde","PontoID":"Ponto 1","Descrição":"Inicio da linha.","IntervaloMin":"0","IntervaloSeg":"0"},
		{"LinhaID":"Campo Água Verde","RoteiroInicio":"Praça","SentidoLinha":"Bairro Água Verde","PontoID":"Ponto 2","Descrição":"-","IntervaloMin":"1","IntervaloSeg":"42"},
		{"LinhaID":"Campo Água Verde","RoteiroInicio":"Praça","SentidoLinha":"Bairro Água Verde","PontoID":"Ponto 3","Descrição":"-","IntervaloMin":"1","IntervaloSeg":"42"},
		{"LinhaID":"Campo Água Verde","RoteiroInicio":"Praça","SentidoLinha":"Bairro Água Verde","PontoID":"Ponto 4","Descrição":"-","IntervaloMin":"1","IntervaloSeg":"42"},
		{"LinhaID":"Campo Água Verde","RoteiroInicio":"Praça","SentidoLinha":"Bairro Água Verde","PontoID":"Ponto 5","Descrição":"-","IntervaloMin":"1","IntervaloSeg":"42"},
		{"LinhaID":"Campo Água Verde","RoteiroInicio":"Praça","SentidoLinha":"Bairro Água Verde","PontoID":"Ponto 6","Descrição":"-","IntervaloMin":"1","IntervaloSeg":"42"},
		{"LinhaID":"Campo Água Verde","RoteiroInicio":"Praça","SentidoLinha":"Bairro Água Verde","PontoID":"Ponto 7","Descrição":"-","IntervaloMin":"1","IntervaloSeg":"42"},
		{"LinhaID":"Campo Água Verde","RoteiroInicio":"Praça","SentidoLinha":"Bairro Água Verde","PontoID":"Ponto 8","Descrição":"-","IntervaloMin":"1","IntervaloSeg":"42"},
		{"LinhaID":"Campo Água Verde","RoteiroInicio":"Praça","SentidoLinha":"Bairro Água Verde","PontoID":"Ponto 9","Descrição":"-","IntervaloMin":"1","IntervaloSeg":"42"},
		{"LinhaID":"Campo Água Verde","RoteiroInicio":"Praça","SentidoLinha":"Bairro Água Verde","PontoID":"Ponto 10","Descrição":"-","IntervaloMin":"1","IntervaloSeg":"42"},
		{"LinhaID":"Campo Água Verde","RoteiroInicio":"Praça","SentidoLinha":"Bairro Água Verde","PontoID":"Ponto 11","Descrição":"-","IntervaloMin":"1","IntervaloSeg":"42"},
		{"LinhaID":"Campo Água Verde","RoteiroInicio":"Praça","SentidoLinha":"Bairro Água Verde","PontoID":"Ponto 12","Descrição":"-","IntervaloMin":"1","IntervaloSeg":"42"},
		{"LinhaID":"Campo Água Verde","RoteiroInicio":"Praça","SentidoLinha":"Bairro Água Verde","PontoID":"Ponto 13","Descrição":"-","IntervaloMin":"1","IntervaloSeg":"42"},
		{"LinhaID":"Campo Água Verde","RoteiroInicio":"Praça","SentidoLinha":"Bairro Água Verde","PontoID":"Ponto 14","Descrição":"-","IntervaloMin":"1","IntervaloSeg":"42"},
		{"LinhaID":"Campo Água Verde","RoteiroInicio":"Praça","SentidoLinha":"Bairro Água Verde","PontoID":"Ponto 15","Descrição":"-","IntervaloMin":"1","IntervaloSeg":"42"},
		{"LinhaID":"Campo Água Verde","RoteiroInicio":"Praça","SentidoLinha":"Bairro Água Verde","PontoID":"Ponto 16","Descrição":"-","IntervaloMin":"1","IntervaloSeg":"42"},
		{"LinhaID":"Campo Água Verde","RoteiroInicio":"Praça","SentidoLinha":"Bairro Água Verde","PontoID":"Ponto 17","Descrição":"-","IntervaloMin":"1","IntervaloSeg":"42"},
		{"LinhaID":"Campo Água Verde","RoteiroInicio":"Praça","SentidoLinha":"Bairro Água Verde","PontoID":"Ponto 18","Descrição":"-","IntervaloMin":"1","IntervaloSeg":"42"},
		{"LinhaID":"Campo Água Verde","RoteiroInicio":"Praça","SentidoLinha":"Bairro Água Verde","PontoID":"Ponto 19","Descrição":"-","IntervaloMin":"1","IntervaloSeg":"42"},
		{"LinhaID":"Campo Água Verde","RoteiroInicio":"Praça","SentidoLinha":"Bairro Água Verde","PontoID":"Ponto 20","Descrição":"-","IntervaloMin":"1","IntervaloSeg":"42"},
		{"LinhaID":"Campo Água Verde","RoteiroInicio":"Praça","SentidoLinha":"Bairro Água Verde","PontoID":"Ponto 21","Descrição":"-","IntervaloMin":"1","IntervaloSeg":"42"},
		{"LinhaID":"Campo Água Verde","RoteiroInicio":"Praça","SentidoLinha":"Bairro Água Verde","PontoID":"Ponto 22","Descrição":"Último ponto antes do retorno para a praça. ","IntervaloMin":"2","IntervaloSeg":"0"},
		{"LinhaID":"Campo Água Verde","RoteiroInicio":"Praça","SentidoLinha":"Praça Lauro Mueller","PontoID":"Ponto 23","Descrição":"-","IntervaloMin":"2","IntervaloSeg":"0"},
		{"LinhaID":"Campo Água Verde","RoteiroInicio":"Praça","SentidoLinha":"Praça Lauro Mueller","PontoID":"Ponto 24","Descrição":"-","IntervaloMin":"2","IntervaloSeg":"0"},
		{"LinhaID":"Campo Água Verde","RoteiroInicio":"Praça","SentidoLinha":"Praça Lauro Mueller","PontoID":"Ponto 25","Descrição":"-","IntervaloMin":"2","IntervaloSeg":"0"},
		{"LinhaID":"Campo Água Verde","RoteiroInicio":"Praça","SentidoLinha":"Praça Lauro Mueller","PontoID":"Ponto 26","Descrição":"-","IntervaloMin":"2","IntervaloSeg":"0"},
		{"LinhaID":"Campo Água Verde","RoteiroInicio":"Praça","SentidoLinha":"Praça Lauro Mueller","PontoID":"Ponto 27","Descrição":"-","IntervaloMin":"2","IntervaloSeg":"0"},
		{"LinhaID":"Campo Água Verde","RoteiroInicio":"Praça","SentidoLinha":"Praça Lauro Mueller","PontoID":"Ponto 28","Descrição":"-","IntervaloMin":"2","IntervaloSeg":"0"},
		{"LinhaID":"Campo Água Verde","RoteiroInicio":"Praça","SentidoLinha":"Praça Lauro Mueller","PontoID":"Ponto 29","Descrição":"-","IntervaloMin":"3","IntervaloSeg":"0"},
		{"LinhaID":"Campo Água Verde","RoteiroInicio":"Praça","SentidoLinha":"Praça Lauro Mueller","PontoID":"Ponto 30","Descrição":"-","IntervaloMin":"2","IntervaloSeg":"0"},
		{"LinhaID":"Campo Água Verde","RoteiroInicio":"Praça","SentidoLinha":"Praça Lauro Mueller","PontoID":"Ponto 31","Descrição":"-","IntervaloMin":"2","IntervaloSeg":"0"},
		{"LinhaID":"Campo Água Verde","RoteiroInicio":"Praça","SentidoLinha":"Praça Lauro Mueller","PontoID":"Ponto 32","Descrição":"-","IntervaloMin":"2","IntervaloSeg":"0"},
		{"LinhaID":"Campo Água Verde","RoteiroInicio":"Praça","SentidoLinha":"Praça Lauro Mueller","PontoID":"Ponto 33","Descrição":"-","IntervaloMin":"2","IntervaloSeg":"0"},
		{"LinhaID":"Campo Água Verde","RoteiroInicio":"Praça","SentidoLinha":"Praça Lauro Mueller","PontoID":"Ponto 34","Descrição":"-","IntervaloMin":"2","IntervaloSeg":"0"},
		{"LinhaID":"Campo Água Verde","RoteiroInicio":"Praça","SentidoLinha":"Praça Lauro Mueller","PontoID":"Ponto 35","Descrição":"-","IntervaloMin":"2","IntervaloSeg":"0"},
		{"LinhaID":"Campo Água Verde","RoteiroInicio":"Praça","SentidoLinha":"Praça Lauro Mueller","PontoID":"Ponto 1","Descrição":"Ponto final. ","IntervaloMin":"2","IntervaloSeg":"0"},
		{"LinhaID":"Aparecida","RoteiroInicio":"Praça","SentidoLinha":"Bairro Piedade","PontoID":"Ponto 1","Descrição":"Ponto inicial.","IntervaloMin":"1","IntervaloSeg":"52"},
		{"LinhaID":"Aparecida","RoteiroInicio":"Praça","SentidoLinha":"Bairro Piedade","PontoID":"Ponto 36","Descrição":"-","IntervaloMin":"1","IntervaloSeg":"52"},
		{"LinhaID":"Aparecida","RoteiroInicio":"Praça","SentidoLinha":"Bairro Piedade","PontoID":"Ponto 37","Descrição":"-","IntervaloMin":"1","IntervaloSeg":"52"},
		{"LinhaID":"Aparecida","RoteiroInicio":"Praça","SentidoLinha":"Bairro Piedade","PontoID":"Ponto 38","Descrição":"-","IntervaloMin":"1","IntervaloSeg":"52"},
		{"LinhaID":"Aparecida","RoteiroInicio":"Praça","SentidoLinha":"Bairro Piedade","PontoID":"Ponto 39","Descrição":"-","IntervaloMin":"1","IntervaloSeg":"52"},
		{"LinhaID":"Aparecida","RoteiroInicio":"Praça","SentidoLinha":"Bairro Piedade","PontoID":"Ponto 40","Descrição":"-","IntervaloMin":"1","IntervaloSeg":"52"},
		{"LinhaID":"Aparecida","RoteiroInicio":"Praça","SentidoLinha":"Bairro Piedade","PontoID":"Ponto 41","Descrição":"-","IntervaloMin":"1","IntervaloSeg":"52"},
		{"LinhaID":"Aparecida","RoteiroInicio":"Praça","SentidoLinha":"Bairro Piedade","PontoID":"Ponto 42","Descrição":"-","IntervaloMin":"1","IntervaloSeg":"52"},
		{"LinhaID":"Aparecida","RoteiroInicio":"Praça","SentidoLinha":"Bairro Piedade","PontoID":"Ponto 43","Descrição":"-","IntervaloMin":"1","IntervaloSeg":"52"},
		{"LinhaID":"Aparecida","RoteiroInicio":"Praça","SentidoLinha":"Centro","PontoID":"Ponto 44","Descrição":"-","IntervaloMin":"1","IntervaloSeg":"52"},
		{"LinhaID":"Aparecida","RoteiroInicio":"Praça","SentidoLinha":"Centro","PontoID":"Ponto 45","Descrição":"-","IntervaloMin":"1","IntervaloSeg":"52"},
		{"LinhaID":"Aparecida","RoteiroInicio":"Praça","SentidoLinha":"Centro","PontoID":"Ponto 46","Descrição":"-","IntervaloMin":"1","IntervaloSeg":"52"},
		{"LinhaID":"Aparecida","RoteiroInicio":"Praça","SentidoLinha":"Centro","PontoID":"Ponto 47","Descrição":"-","IntervaloMin":"1","IntervaloSeg":"52"},
		{"LinhaID":"Aparecida","RoteiroInicio":"Praça","SentidoLinha":"Centro","PontoID":"Ponto 48","Descrição":"-","IntervaloMin":"1","IntervaloSeg":"52"},
		{"LinhaID":"Aparecida","RoteiroInicio":"Praça","SentidoLinha":"Centro","PontoID":"Ponto 49","Descrição":"-","IntervaloMin":"1","IntervaloSeg":"52"},
		{"LinhaID":"Aparecida","RoteiroInicio":"Praça","SentidoLinha":"Centro","PontoID":"Ponto 50","Descrição":"-","IntervaloMin":"1","IntervaloSeg":"52"},
		{"LinhaID":"Aparecida","RoteiroInicio":"Praça","SentidoLinha":"Centro","PontoID":"Ponto 51","Descrição":"-","IntervaloMin":"1","IntervaloSeg":"52"},
		{"LinhaID":"Aparecida","RoteiroInicio":"Praça","SentidoLinha":"Centro","PontoID":"Ponto 52","Descrição":"-","IntervaloMin":"1","IntervaloSeg":"52"},
		{"LinhaID":"Aparecida","RoteiroInicio":"Praça","SentidoLinha":"Centro","PontoID":"Ponto 53","Descrição":"-","IntervaloMin":"1","IntervaloSeg":"52"},
		{"LinhaID":"Aparecida","RoteiroInicio":"Praça","SentidoLinha":"Bairro Jardim Esperança","PontoID":"Ponto 54","Descrição":"-","IntervaloMin":"1","IntervaloSeg":"52"},
		{"LinhaID":"Aparecida","RoteiroInicio":"Praça","SentidoLinha":"Bairro Jardim Esperança","PontoID":"Ponto 55","Descrição":"-","IntervaloMin":"1","IntervaloSeg":"52"},
		{"LinhaID":"Aparecida","RoteiroInicio":"Praça","SentidoLinha":"Bairro Jardim Esperança","PontoID":"Ponto 56","Descrição":"-","IntervaloMin":"1","IntervaloSeg":"52"},
		{"LinhaID":"Aparecida","RoteiroInicio":"Praça","SentidoLinha":"Bairro Jardim Esperança","PontoID":"Ponto 57","Descrição":"-","IntervaloMin":"1","IntervaloSeg":"52"},
		{"LinhaID":"Aparecida","RoteiroInicio":"Praça","SentidoLinha":"Bairro Jardim Esperança","PontoID":"Ponto 58","Descrição":"-","IntervaloMin":"1","IntervaloSeg":"52"},
		{"LinhaID":"Aparecida","RoteiroInicio":"Praça","SentidoLinha":"Bairro Jardim Esperança","PontoID":"Ponto 59","Descrição":"-","IntervaloMin":"1","IntervaloSeg":"52"},
		{"LinhaID":"Aparecida","RoteiroInicio":"Praça","SentidoLinha":"Bairro Jardim Esperança","PontoID":"Ponto 60","Descrição":"-","IntervaloMin":"1","IntervaloSeg":"52"},
		{"LinhaID":"Aparecida","RoteiroInicio":"Praça","SentidoLinha":"Bairro Jardim Esperança","PontoID":"Ponto 61","Descrição":"-","IntervaloMin":"1","IntervaloSeg":"52"},
		{"LinhaID":"Aparecida","RoteiroInicio":"Praça","SentidoLinha":"Bairro Jardim Esperança","PontoID":"Ponto 62","Descrição":"-","IntervaloMin":"1","IntervaloSeg":"52"},
		{"LinhaID":"Aparecida","RoteiroInicio":"Praça","SentidoLinha":"Centro","PontoID":"Ponto 63","Descrição":"-","IntervaloMin":"1","IntervaloSeg":"52"},
		{"LinhaID":"Aparecida","RoteiroInicio":"Praça","SentidoLinha":"Centro","PontoID":"Ponto 64","Descrição":"-","IntervaloMin":"1","IntervaloSeg":"52"},
		{"LinhaID":"Aparecida","RoteiroInicio":"Praça","SentidoLinha":"Centro","PontoID":"Ponto 65","Descrição":"-","IntervaloMin":"1","IntervaloSeg":"52"},
		{"LinhaID":"Aparecida","RoteiroInicio":"Praça","SentidoLinha":"Centro","PontoID":"Ponto 66","Descrição":"-","IntervaloMin":"1","IntervaloSeg":"52"},
		{"LinhaID":"Aparecida","RoteiroInicio":"Praça","SentidoLinha":"Centro","PontoID":"Ponto 67","Descrição":"Ponto final. ","IntervaloMin":"1","IntervaloSeg":"52"},
		{"LinhaID":"Cohab I, II","RoteiroInicio":"Praça","SentidoLinha":"Sentido Fricassa","PontoID":"Ponto 1","Descrição":"Ponto incial. ","IntervaloMin":"1","IntervaloSeg":"37"},
		{"LinhaID":"Cohab I, II","RoteiroInicio":"Praça","SentidoLinha":"Sentido Fricassa","PontoID":"Ponto 68","Descrição":"-","IntervaloMin":"1","IntervaloSeg":"37"},
		{"LinhaID":"Cohab I, II","RoteiroInicio":"Praça","SentidoLinha":"Sentido Fricassa","PontoID":"Ponto 69","Descrição":"-","IntervaloMin":"1","IntervaloSeg":"37"},
		{"LinhaID":"Cohab I, II","RoteiroInicio":"Praça","SentidoLinha":"Sentido Fricassa","PontoID":"Ponto 70","Descrição":"-","IntervaloMin":"1","IntervaloSeg":"37"},
		{"LinhaID":"Cohab I, II","RoteiroInicio":"Praça","SentidoLinha":"Sentido Fricassa","PontoID":"Ponto 71","Descrição":"-","IntervaloMin":"1","IntervaloSeg":"37"},
		{"LinhaID":"Cohab I, II","RoteiroInicio":"Praça","SentidoLinha":"Sentido Fricassa","PontoID":"Ponto 72","Descrição":"-","IntervaloMin":"1","IntervaloSeg":"37"},
		{"LinhaID":"Cohab I, II","RoteiroInicio":"Praça","SentidoLinha":"Sentido Fricassa","PontoID":"Ponto 73","Descrição":"-","IntervaloMin":"1","IntervaloSeg":"37"},
		{"LinhaID":"Cohab I, II","RoteiroInicio":"Praça","SentidoLinha":"Sentido Fricassa","PontoID":"Ponto 74","Descrição":"-","IntervaloMin":"1","IntervaloSeg":"37"},
		{"LinhaID":"Cohab I, II","RoteiroInicio":"Praça","SentidoLinha":"Sentido Fricassa","PontoID":"Ponto 75","Descrição":"-","IntervaloMin":"1","IntervaloSeg":"37"},
		{"LinhaID":"Cohab I, II","RoteiroInicio":"Praça","SentidoLinha":"Sentido Fricassa","PontoID":"Ponto 76","Descrição":"-","IntervaloMin":"1","IntervaloSeg":"37"},
		{"LinhaID":"Cohab I, II","RoteiroInicio":"Praça","SentidoLinha":"Sentido Fricassa","PontoID":"Ponto 77","Descrição":"-","IntervaloMin":"1","IntervaloSeg":"37"},
		{"LinhaID":"Cohab I, II","RoteiroInicio":"Praça","SentidoLinha":"Centro ","PontoID":"Ponto 78","Descrição":"-","IntervaloMin":"1","IntervaloSeg":"37"},
		{"LinhaID":"Cohab I, II","RoteiroInicio":"Praça","SentidoLinha":"Centro ","PontoID":"Ponto 79","Descrição":"-","IntervaloMin":"1","IntervaloSeg":"37"},
		{"LinhaID":"Cohab I, II","RoteiroInicio":"Praça","SentidoLinha":"Centro ","PontoID":"Ponto 80","Descrição":"-","IntervaloMin":"1","IntervaloSeg":"37"},
		{"LinhaID":"Cohab I, II","RoteiroInicio":"Praça","SentidoLinha":"Centro ","PontoID":"Ponto 81","Descrição":"-","IntervaloMin":"1","IntervaloSeg":"37"},
		{"LinhaID":"Cohab I, II","RoteiroInicio":"Praça","SentidoLinha":"Centro ","PontoID":"Ponto 82","Descrição":"-","IntervaloMin":"1","IntervaloSeg":"37"},
		{"LinhaID":"Cohab I, II","RoteiroInicio":"Praça","SentidoLinha":"Centro ","PontoID":"Ponto 64","Descrição":"-","IntervaloMin":"1","IntervaloSeg":"37"},
		{"LinhaID":"Cohab I, II","RoteiroInicio":"Praça","SentidoLinha":"Centro ","PontoID":"Ponto 83","Descrição":"-","IntervaloMin":"1","IntervaloSeg":"37"},
		{"LinhaID":"Cohab I, II","RoteiroInicio":"Praça","SentidoLinha":"Centro ","PontoID":"Ponto 84","Descrição":"-","IntervaloMin":"1","IntervaloSeg":"37"},
		{"LinhaID":"Cohab I, II","RoteiroInicio":"Praça","SentidoLinha":"Centro ","PontoID":"Ponto 36","Descrição":"-","IntervaloMin":"1","IntervaloSeg":"37"},
		{"LinhaID":"Cohab I, II","RoteiroInicio":"Praça","SentidoLinha":"Bairro Água Verde","PontoID":"Ponto 85","Descrição":"-","IntervaloMin":"1","IntervaloSeg":"37"},
		{"LinhaID":"Cohab I, II","RoteiroInicio":"Praça","SentidoLinha":"Bairro Água Verde","PontoID":"Ponto 86","Descrição":"-","IntervaloMin":"1","IntervaloSeg":"37"},
		{"LinhaID":"Cohab I, II","RoteiroInicio":"Praça","SentidoLinha":"Bairro Água Verde","PontoID":"Ponto 87","Descrição":"-","IntervaloMin":"1","IntervaloSeg":"37"},
		{"LinhaID":"Cohab I, II","RoteiroInicio":"Praça","SentidoLinha":"Bairro Água Verde","PontoID":"Ponto 88","Descrição":"-","IntervaloMin":"1","IntervaloSeg":"37"},
		{"LinhaID":"Cohab I, II","RoteiroInicio":"Praça","SentidoLinha":"Bairro Água Verde","PontoID":"Ponto 89","Descrição":"-","IntervaloMin":"1","IntervaloSeg":"37"},
		{"LinhaID":"Cohab I, II","RoteiroInicio":"Praça","SentidoLinha":"Bairro Água Verde","PontoID":"Ponto 90","Descrição":"-","IntervaloMin":"1","IntervaloSeg":"37"},
		{"LinhaID":"Cohab I, II","RoteiroInicio":"Praça","SentidoLinha":"Bairro Água Verde","PontoID":"Ponto 91","Descrição":"-","IntervaloMin":"1","IntervaloSeg":"37"},
		{"LinhaID":"Cohab I, II","RoteiroInicio":"Praça","SentidoLinha":"Bairro Água Verde","PontoID":"Ponto 92","Descrição":"-","IntervaloMin":"1","IntervaloSeg":"37"},
		{"LinhaID":"Cohab I, II","RoteiroInicio":"Praça","SentidoLinha":"Centro","PontoID":"Ponto 93","Descrição":"-","IntervaloMin":"1","IntervaloSeg":"37"},
		{"LinhaID":"Cohab I, II","RoteiroInicio":"Praça","SentidoLinha":"Centro","PontoID":"Ponto 94","Descrição":"-","IntervaloMin":"1","IntervaloSeg":"37"},
		{"LinhaID":"Cohab I, II","RoteiroInicio":"Praça","SentidoLinha":"Centro","PontoID":"Ponto 95","Descrição":"-","IntervaloMin":"1","IntervaloSeg":"37"},
		{"LinhaID":"Cohab I, II","RoteiroInicio":"Praça","SentidoLinha":"Centro","PontoID":"Ponto 96","Descrição":"-","IntervaloMin":"1","IntervaloSeg":"37"},
		{"LinhaID":"Cohab I, II","RoteiroInicio":"Praça","SentidoLinha":"Centro","PontoID":"Ponto 97","Descrição":"-","IntervaloMin":"1","IntervaloSeg":"37"},
		{"LinhaID":"Cohab I, II","RoteiroInicio":"Praça","SentidoLinha":"Centro","PontoID":"Ponto 98","Descrição":"-","IntervaloMin":"1","IntervaloSeg":"37"},
		{"LinhaID":"Cohab I, II","RoteiroInicio":"Praça","SentidoLinha":"Centro","PontoID":"Ponto 99","Descrição":"-","IntervaloMin":"1","IntervaloSeg":"37"},
		{"LinhaID":"Cohab I, II","RoteiroInicio":"Praça","SentidoLinha":"Centro","PontoID":"Ponto 100","Descrição":"-","IntervaloMin":"1","IntervaloSeg":"37"},
		{"LinhaID":"Cohab I, II","RoteiroInicio":"Praça","SentidoLinha":"Centro","PontoID":"Ponto 53","Descrição":"-","IntervaloMin":"1","IntervaloSeg":"37"},
		{"LinhaID":"Cohab I, II","RoteiroInicio":"Praça","SentidoLinha":"Centro","PontoID":"Ponto 1","Descrição":"Ponto final. ","IntervaloMin":"1","IntervaloSeg":"37"}
	]
}