{
  "versao": {
	"DataHora":"2018/10/25 19:30",
	"ID":"1.2",
	"OBS":"Implementação da linha Água Verde com seus pontos reais."
  },

  "pontos": [
		{"PontoID":"Ponto 1","Latitude":"-26.17371","Longitude":"-50.39008","Comentario ":"Praça Lauro Mueller","SentidoPonto":"Bairro"},
		{"PontoID":"Ponto 2","Latitude":"-26.17314","Longitude":"-50.38816","Comentario ":"Ponto virtual","SentidoPonto":"Bairro"},
		{"PontoID":"Ponto 3","Latitude":"-26.17154","Longitude":"-50.38456","Comentario ":"Ponto virtual","SentidoPonto":"Bairro"},
		{"PontoID":"Ponto 4","Latitude":"-26.1735","Longitude":"-50.37932","Comentario ":"Ponto virtual","SentidoPonto":"Bairro"},
		{"PontoID":"Ponto 5","Latitude":"-26.17628","Longitude":"-50.37574","Comentario ":"Ponto virtual","SentidoPonto":"Bairro"},
		{"PontoID":"Ponto 6","Latitude":"-26.18053","Longitude":"-50.37033","Comentario ":"Ponto virtual","SentidoPonto":"Bairro"},
		{"PontoID":"Ponto 7","Latitude":"-26.18301","Longitude":"-50.3672","Comentario ":"IFSC","SentidoPonto":"Bairro"},
		{"PontoID":"Ponto 8","Latitude":"-26.18411","Longitude":"-50.36288","Comentario ":"Ponto virtual","SentidoPonto":"Bairro"},
		{"PontoID":"Ponto 9","Latitude":"-26.18573","Longitude":"-50.36077","Comentario ":"Ponto virtual","SentidoPonto":"Bairro"},
		{"PontoID":"Ponto 10","Latitude":"-26.18674","Longitude":"-50.36037","Comentario ":"Ponto virtual","SentidoPonto":"Bairro"},
		{"PontoID":"Ponto 11","Latitude":"-26.18796","Longitude":"-50.36464","Comentario ":"Ponto virtual","SentidoPonto":"Bairro"},
		{"PontoID":"Ponto 12","Latitude":"-26.18869","Longitude":"-50.36881","Comentario ":"Ponto virtual","SentidoPonto":"Bairro"},
		{"PontoID":"Ponto 13","Latitude":"-26.18942","Longitude":"-50.37346","Comentario ":"Ponto virtual. Próx. retifica Motocar","SentidoPonto":"Bairro"},
		{"PontoID":"Ponto 14","Latitude":"-26.1907","Longitude":"-50.37833","Comentario ":"Ponto virtual","SentidoPonto":"Bairro"},
		{"PontoID":"Ponto 15","Latitude":"-26.19408","Longitude":"-50.378","Comentario ":"Ponto virtual","SentidoPonto":"Bairro"},
		{"PontoID":"Ponto 16","Latitude":"-26.19588","Longitude":"-50.37824","Comentario ":"Ponto virtual","SentidoPonto":"Bairro"},
		{"PontoID":"Ponto 17","Latitude":"-26.19959","Longitude":"-50.37876","Comentario ":"Ponto virtual","SentidoPonto":"Bairro"},
		{"PontoID":"Ponto 18","Latitude":"-26.20107","Longitude":"-50.38282","Comentario ":"Ponto virtual","SentidoPonto":"Bairro"},
		{"PontoID":"Ponto 19","Latitude":"-26.203022","Longitude":"-50.384556","Comentario ":"Ponto Físico","SentidoPonto":"Bairro"},
		{"PontoID":"Ponto 20","Latitude":"-26.205336","Longitude":"-50.383465","Comentario ":"Ponto Físico","SentidoPonto":"Bairro"},
		{"PontoID":"Ponto 21","Latitude":"-26.20448","Longitude":"-50.37991","Comentario ":"Ponto virtual","SentidoPonto":"Bairro"},
		{"PontoID":"Ponto 22","Latitude":"-26.200403","Longitude":"-50.37675","Comentario ":"Ponto Físico","SentidoPonto":"Bairro"},
		{"PontoID":"Ponto 23","Latitude":"-26.1979","Longitude":"-50.37772","Comentario ":"Ponto virtual","SentidoPonto":"Praça"},
		{"PontoID":"Ponto 24","Latitude":"-26.19376","Longitude":"-50.37713","Comentario ":"Ponto Físico. Próximo da Escola Estadual Emília Ferrero","SentidoPonto":"Praça"},
		{"PontoID":"Ponto 25","Latitude":"-26.19062","Longitude":"-50.37832","Comentario ":"Ponto virtual","SentidoPonto":"Praça"},
		{"PontoID":"Ponto 26","Latitude":"-26.18956","Longitude":"-50.37293","Comentario ":"Ponto virtual","SentidoPonto":"Praça"},
		{"PontoID":"Ponto 27","Latitude":"-26.18818","Longitude":"-50.36438","Comentario ":"Ponto virtual, próximo ao Procopiak","SentidoPonto":"Praça"},
		{"PontoID":"Ponto 28","Latitude":"-26.18422","Longitude":"-50.36262","Comentario ":"Ponto Físico","SentidoPonto":"Praça"},
		{"PontoID":"Ponto 29","Latitude":"-26.18318","Longitude":"-50.36685","Comentario ":"Ponto Físico","SentidoPonto":"Praça"},
		{"PontoID":"Ponto 30","Latitude":"-26.181576","Longitude":"-50.36902","Comentario ":"Ponto Físico","SentidoPonto":"Praça"},
		{"PontoID":"Ponto 31","Latitude":"-26.179176","Longitude":"-50.371998","Comentario ":"Ponto Físico","SentidoPonto":"Praça"},
		{"PontoID":"Ponto 32","Latitude":"-26.176903","Longitude":"-50.37489","Comentario ":"Ponto Físico","SentidoPonto":"Praça"},
		{"PontoID":"Ponto 33","Latitude":"-26.173763","Longitude":"-50.378975","Comentario ":"Ponto Físico","SentidoPonto":"Praça"},
		{"PontoID":"Ponto 34","Latitude":"-26.17144","Longitude":"-50.38373","Comentario ":"Ponto virtual. Próximo ao posto Guapo.","SentidoPonto":"Praça"},
		{"PontoID":"Ponto 35","Latitude":"-26.17224","Longitude":"-50.38723","Comentario ":"Ponto virtual.","SentidoPonto":"Praça"}
  ],
  
  "linhas":[
	  {"LinhaID":"Aparecida",
	  "RoteiroInicio":"Terminal urbano",
	  "RoteiroFim":"Bairro Aparecida",
	  "RoteiroPontos":"Ponto 1, Ponto 36, Ponto 37, Ponto 38, Ponto 39, Ponto 40, Ponto 41, Ponto 42, Ponto 43, Ponto 44, Ponto 45, Ponto 46, Ponto 47, Ponto 48, Ponto 49, Ponto 50, Ponto 51, Ponto 52, Ponto 53, Ponto 54, Ponto 55, Ponto 56, Ponto 57, Ponto 58, Ponto 59, Ponto 60, Ponto 61, Ponto 62, Ponto 63, Ponto 64, Ponto 65, Ponto 66, Ponto 67"
	  },
	  {"LinhaID":"Cohab I, II",
	  "RoteiroInicio":"Terminal Urbano",
	  "RoteiroFim":"Bairro Cohab II",
	  "RoteiroPontos":"Ponto 1, Ponto 68, Ponto 69, Ponto 70, Ponto 71, Ponto 72, Ponto 73, Ponto 74, Ponto 75, Ponto 76, Ponto 77, Ponto 78, Ponto 79, Ponto 80, Ponto 81, Ponto 82, Ponto 64, Ponto 83, Ponto 84, Ponto 36, Ponto 85, Ponto 86, Ponto 87, Ponto 88, Ponto 89, Ponto 90, Ponto 91, Ponto 92, Ponto 93, Ponto 94, Ponto 95, Ponto 96, Ponto 97, Ponto 98, Ponto 99, Ponto 100, Ponto 53, Ponto 1"
	  },	    
	  {"LinhaID":"Campo Água Verde",
	  "RoteiroPontos":"Ponto 1, Ponto 2, Ponto 3, Ponto 4, Ponto 5, Ponto 6, Ponto 7, Ponto 8, Ponto 9, Ponto 10, Ponto 11, Ponto 12, Ponto 13, Ponto 14, Ponto 15, Ponto 16, Ponto 17, Ponto 18, Ponto 19, Ponto 20, Ponto 21, Ponto 22, Ponto 23, Ponto 24, Ponto 25, Ponto 26, Ponto 27, Ponto 28, Ponto 29, Ponto 30, Ponto 31, Ponto 32, Ponto 33, Ponto 34, Ponto 35"
	  }
  ],
  
  "horaLinha":[
		{"LinhaID":"Cohab I, II","RoteiroInicio":"Terminal Urbano","RoteiroFim":"Bairro Cohab I","DiaSemana":"2, 3, 4, 5, 6","Hora":"06:05"},
		{"LinhaID":"Cohab I, II","RoteiroInicio":"Terminal Urbano","RoteiroFim":"Bairro Cohab I","DiaSemana":"2, 3, 4, 5, 6","Hora":"07:05"},
		{"LinhaID":"Cohab I, II","RoteiroInicio":"Terminal Urbano","RoteiroFim":"Bairro Cohab I","DiaSemana":"2, 3, 4, 5, 6","Hora":"08:05"},
		{"LinhaID":"Cohab I, II","RoteiroInicio":"Terminal Urbano","RoteiroFim":"Bairro Cohab I","DiaSemana":"2, 3, 4, 5, 6","Hora":"09:05"},
		{"LinhaID":"Cohab I, II","RoteiroInicio":"Terminal Urbano","RoteiroFim":"Bairro Cohab I","DiaSemana":"2, 3, 4, 5, 6","Hora":"10:05"},
		{"LinhaID":"Cohab I, II","RoteiroInicio":"Terminal Urbano","RoteiroFim":"Bairro Cohab I","DiaSemana":"2, 3, 4, 5, 6","Hora":"11:05"},
		{"LinhaID":"Cohab I, II","RoteiroInicio":"Terminal Urbano","RoteiroFim":"Bairro Cohab I","DiaSemana":"2, 3, 4, 5, 6","Hora":"12:05"},
		{"LinhaID":"Cohab I, II","RoteiroInicio":"Terminal Urbano","RoteiroFim":"Bairro Cohab I","DiaSemana":"2, 3, 4, 5, 6","Hora":"13:05"},
		{"LinhaID":"Cohab I, II","RoteiroInicio":"Terminal Urbano","RoteiroFim":"Bairro Cohab I","DiaSemana":"2, 3, 4, 5, 6","Hora":"14:05"},
		{"LinhaID":"Cohab I, II","RoteiroInicio":"Terminal Urbano","RoteiroFim":"Bairro Cohab I","DiaSemana":"2, 3, 4, 5, 6","Hora":"15:05"},
		{"LinhaID":"Cohab I, II","RoteiroInicio":"Terminal Urbano","RoteiroFim":"Bairro Cohab I","DiaSemana":"2, 3, 4, 5, 6","Hora":"16:05"},
		{"LinhaID":"Cohab I, II","RoteiroInicio":"Terminal Urbano","RoteiroFim":"Bairro Cohab I","DiaSemana":"2, 3, 4, 5, 6","Hora":"17:05"},
		{"LinhaID":"Cohab I, II","RoteiroInicio":"Terminal Urbano","RoteiroFim":"Bairro Cohab I","DiaSemana":"2, 3, 4, 5, 6","Hora":"18:05"},
		{"LinhaID":"Cohab I, II","RoteiroInicio":"Terminal Urbano","RoteiroFim":"Bairro Cohab I","DiaSemana":"2, 3, 4, 5, 6","Hora":"19:05"},
		{"LinhaID":"Cohab I, II","RoteiroInicio":"Terminal Urbano","RoteiroFim":"Bairro Cohab I","DiaSemana":"7","Hora":"06:05"},
		{"LinhaID":"Cohab I, II","RoteiroInicio":"Terminal Urbano","RoteiroFim":"Bairro Cohab I","DiaSemana":"7","Hora":"07:05"},
		{"LinhaID":"Cohab I, II","RoteiroInicio":"Terminal Urbano","RoteiroFim":"Bairro Cohab I","DiaSemana":"7","Hora":"08:05"},
		{"LinhaID":"Cohab I, II","RoteiroInicio":"Terminal Urbano","RoteiroFim":"Bairro Cohab I","DiaSemana":"7","Hora":"09:05"},
		{"LinhaID":"Cohab I, II","RoteiroInicio":"Terminal Urbano","RoteiroFim":"Bairro Cohab I","DiaSemana":"7","Hora":"10:05"},
		{"LinhaID":"Cohab I, II","RoteiroInicio":"Terminal Urbano","RoteiroFim":"Bairro Cohab I","DiaSemana":"7","Hora":"11:05"},
		{"LinhaID":"Cohab I, II","RoteiroInicio":"Terminal Urbano","RoteiroFim":"Bairro Cohab I","DiaSemana":"7","Hora":"12:05"},
		{"LinhaID":"Cohab I, II","RoteiroInicio":"Terminal Urbano","RoteiroFim":"Bairro Cohab I","DiaSemana":"7","Hora":"13:05"},
		{"LinhaID":"Cohab I, II","RoteiroInicio":"Terminal Urbano","RoteiroFim":"Bairro Cohab I","DiaSemana":"7","Hora":"14:05"},
		{"LinhaID":"Cohab I, II","RoteiroInicio":"Terminal Urbano","RoteiroFim":"Bairro Cohab I","DiaSemana":"7","Hora":"15:05"},
		{"LinhaID":"Cohab I, II","RoteiroInicio":"Terminal Urbano","RoteiroFim":"Bairro Cohab I","DiaSemana":"7","Hora":"16:05"},
		{"LinhaID":"Cohab I, II","RoteiroInicio":"Terminal Urbano","RoteiroFim":"Bairro Cohab I","DiaSemana":"7","Hora":"17:05"},
		{"LinhaID":"Cohab I, II","RoteiroInicio":"Terminal Urbano","RoteiroFim":"Bairro Cohab I","DiaSemana":"7","Hora":"18:05"},
		{"LinhaID":"Cohab I, II","RoteiroInicio":"Terminal Urbano","RoteiroFim":"Bairro Cohab I","DiaSemana":"1, 0","Hora":"09:00"},
		{"LinhaID":"Cohab I, II","RoteiroInicio":"Terminal Urbano","RoteiroFim":"Bairro Cohab I","DiaSemana":"1, 0","Hora":"10:00"},
		{"LinhaID":"Cohab I, II","RoteiroInicio":"Terminal Urbano","RoteiroFim":"Bairro Cohab I","DiaSemana":"1, 0","Hora":"15:00"},
		{"LinhaID":"Cohab I, II","RoteiroInicio":"Terminal Urbano","RoteiroFim":"Bairro Cohab I","DiaSemana":"1, 0","Hora":"16:00"},
		{"LinhaID":"Cohab I, II","RoteiroInicio":"Terminal Urbano","RoteiroFim":"Bairro Cohab I","DiaSemana":"1, 0","Hora":"17:00"},
		{"LinhaID":"Campo Água Verde","RoteiroInicio":"Terminal Urbano","RoteiroFim":"Bairro Campo Água Verde","DiaSemana":"2, 3, 4, 5, 6","Hora":"06:05"},
		{"LinhaID":"Campo Água Verde","RoteiroInicio":"Terminal Urbano","RoteiroFim":"Bairro Campo Água Verde","DiaSemana":"2, 3, 4, 5, 6","Hora":"07:05"},
		{"LinhaID":"Campo Água Verde","RoteiroInicio":"Terminal Urbano","RoteiroFim":"Bairro Campo Água Verde","DiaSemana":"2, 3, 4, 5, 6","Hora":"08:05"},
		{"LinhaID":"Campo Água Verde","RoteiroInicio":"Terminal Urbano","RoteiroFim":"Bairro Campo Água Verde","DiaSemana":"2, 3, 4, 5, 6","Hora":"09:05"},
		{"LinhaID":"Campo Água Verde","RoteiroInicio":"Terminal Urbano","RoteiroFim":"Bairro Campo Água Verde","DiaSemana":"2, 3, 4, 5, 6","Hora":"10:05"},
		{"LinhaID":"Campo Água Verde","RoteiroInicio":"Terminal Urbano","RoteiroFim":"Bairro Campo Água Verde","DiaSemana":"2, 3, 4, 5, 6","Hora":"11:05"},
		{"LinhaID":"Campo Água Verde","RoteiroInicio":"Terminal Urbano","RoteiroFim":"Bairro Campo Água Verde","DiaSemana":"2, 3, 4, 5, 6","Hora":"12:05"},
		{"LinhaID":"Campo Água Verde","RoteiroInicio":"Terminal Urbano","RoteiroFim":"Bairro Campo Água Verde","DiaSemana":"2, 3, 4, 5, 6","Hora":"13:05"},
		{"LinhaID":"Campo Água Verde","RoteiroInicio":"Terminal Urbano","RoteiroFim":"Bairro Campo Água Verde","DiaSemana":"2, 3, 4, 5, 6","Hora":"14:05"},
		{"LinhaID":"Campo Água Verde","RoteiroInicio":"Terminal Urbano","RoteiroFim":"Bairro Campo Água Verde","DiaSemana":"2, 3, 4, 5, 6","Hora":"15:05"},
		{"LinhaID":"Campo Água Verde","RoteiroInicio":"Terminal Urbano","RoteiroFim":"Bairro Campo Água Verde","DiaSemana":"2, 3, 4, 5, 6","Hora":"16:05"},
		{"LinhaID":"Campo Água Verde","RoteiroInicio":"Terminal Urbano","RoteiroFim":"Bairro Campo Água Verde","DiaSemana":"2, 3, 4, 5, 6","Hora":"17:05"},
		{"LinhaID":"Campo Água Verde","RoteiroInicio":"Terminal Urbano","RoteiroFim":"Bairro Campo Água Verde","DiaSemana":"2, 3, 4, 5, 6","Hora":"18:05"},
		{"LinhaID":"Campo Água Verde","RoteiroInicio":"Terminal Urbano","RoteiroFim":"Bairro Campo Água Verde","DiaSemana":"2, 3, 4, 5, 6","Hora":"19:05"},
		{"LinhaID":"Campo Água Verde","RoteiroInicio":"Bairro Campo Água Verde","RoteiroFim":"Terminal Urbano","DiaSemana":"2, 3, 4, 5, 6","Hora":"06:35"},
		{"LinhaID":"Campo Água Verde","RoteiroInicio":"Bairro Campo Água Verde","RoteiroFim":"Terminal Urbano","DiaSemana":"2, 3, 4, 5, 6","Hora":"07:35"},
		{"LinhaID":"Campo Água Verde","RoteiroInicio":"Bairro Campo Água Verde","RoteiroFim":"Terminal Urbano","DiaSemana":"2, 3, 4, 5, 6","Hora":"08:35"},
		{"LinhaID":"Campo Água Verde","RoteiroInicio":"Bairro Campo Água Verde","RoteiroFim":"Terminal Urbano","DiaSemana":"2, 3, 4, 5, 6","Hora":"09:35"},
		{"LinhaID":"Campo Água Verde","RoteiroInicio":"Bairro Campo Água Verde","RoteiroFim":"Terminal Urbano","DiaSemana":"2, 3, 4, 5, 6","Hora":"10:35"},
		{"LinhaID":"Campo Água Verde","RoteiroInicio":"Bairro Campo Água Verde","RoteiroFim":"Terminal Urbano","DiaSemana":"2, 3, 4, 5, 6","Hora":"11:35"},
		{"LinhaID":"Campo Água Verde","RoteiroInicio":"Bairro Campo Água Verde","RoteiroFim":"Terminal Urbano","DiaSemana":"2, 3, 4, 5, 6","Hora":"12:35"},
		{"LinhaID":"Campo Água Verde","RoteiroInicio":"Bairro Campo Água Verde","RoteiroFim":"Terminal Urbano","DiaSemana":"2, 3, 4, 5, 6","Hora":"13:35"},
		{"LinhaID":"Campo Água Verde","RoteiroInicio":"Bairro Campo Água Verde","RoteiroFim":"Terminal Urbano","DiaSemana":"2, 3, 4, 5, 6","Hora":"14:35"},
		{"LinhaID":"Campo Água Verde","RoteiroInicio":"Bairro Campo Água Verde","RoteiroFim":"Terminal Urbano","DiaSemana":"2, 3, 4, 5, 6","Hora":"15:35"},
		{"LinhaID":"Campo Água Verde","RoteiroInicio":"Bairro Campo Água Verde","RoteiroFim":"Terminal Urbano","DiaSemana":"2, 3, 4, 5, 6","Hora":"16:35"},
		{"LinhaID":"Campo Água Verde","RoteiroInicio":"Bairro Campo Água Verde","RoteiroFim":"Terminal Urbano","DiaSemana":"2, 3, 4, 5, 6","Hora":"17:35"},
		{"LinhaID":"Campo Água Verde","RoteiroInicio":"Bairro Campo Água Verde","RoteiroFim":"Terminal Urbano","DiaSemana":"2, 3, 4, 5, 6","Hora":"18:35"},
		{"LinhaID":"Campo Água Verde","RoteiroInicio":"Bairro Campo Água Verde","RoteiroFim":"Terminal Urbano","DiaSemana":"2, 3, 4, 5, 6","Hora":"19:35"},
		{"LinhaID":"Campo Água Verde","RoteiroInicio":"Terminal Urbano","RoteiroFim":"Bairro Campo Água Verde","DiaSemana":"7","Hora":"06:05"},
		{"LinhaID":"Campo Água Verde","RoteiroInicio":"Terminal Urbano","RoteiroFim":"Bairro Campo Água Verde","DiaSemana":"7","Hora":"07:05"},
		{"LinhaID":"Campo Água Verde","RoteiroInicio":"Terminal Urbano","RoteiroFim":"Bairro Campo Água Verde","DiaSemana":"7","Hora":"08:05"},
		{"LinhaID":"Campo Água Verde","RoteiroInicio":"Terminal Urbano","RoteiroFim":"Bairro Campo Água Verde","DiaSemana":"7","Hora":"09:05"},
		{"LinhaID":"Campo Água Verde","RoteiroInicio":"Terminal Urbano","RoteiroFim":"Bairro Campo Água Verde","DiaSemana":"7","Hora":"10:05"},
		{"LinhaID":"Campo Água Verde","RoteiroInicio":"Terminal Urbano","RoteiroFim":"Bairro Campo Água Verde","DiaSemana":"7","Hora":"11:05"},
		{"LinhaID":"Campo Água Verde","RoteiroInicio":"Terminal Urbano","RoteiroFim":"Bairro Campo Água Verde","DiaSemana":"7","Hora":"12:05"},
		{"LinhaID":"Campo Água Verde","RoteiroInicio":"Terminal Urbano","RoteiroFim":"Bairro Campo Água Verde","DiaSemana":"7","Hora":"13:05"},
		{"LinhaID":"Campo Água Verde","RoteiroInicio":"Terminal Urbano","RoteiroFim":"Bairro Campo Água Verde","DiaSemana":"7","Hora":"14:05"},
		{"LinhaID":"Campo Água Verde","RoteiroInicio":"Terminal Urbano","RoteiroFim":"Bairro Campo Água Verde","DiaSemana":"7","Hora":"15:05"},
		{"LinhaID":"Campo Água Verde","RoteiroInicio":"Terminal Urbano","RoteiroFim":"Bairro Campo Água Verde","DiaSemana":"7","Hora":"16:05"},
		{"LinhaID":"Campo Água Verde","RoteiroInicio":"Terminal Urbano","RoteiroFim":"Bairro Campo Água Verde","DiaSemana":"7","Hora":"17:05"},
		{"LinhaID":"Campo Água Verde","RoteiroInicio":"Terminal Urbano","RoteiroFim":"Bairro Campo Água Verde","DiaSemana":"7","Hora":"18:05"},
		{"LinhaID":"Campo Água Verde","RoteiroInicio":"Bairro Campo Água Verde","RoteiroFim":"Terminal Urbano","DiaSemana":"7","Hora":"06:35"},
		{"LinhaID":"Campo Água Verde","RoteiroInicio":"Bairro Campo Água Verde","RoteiroFim":"Terminal Urbano","DiaSemana":"7","Hora":"07:35"},
		{"LinhaID":"Campo Água Verde","RoteiroInicio":"Bairro Campo Água Verde","RoteiroFim":"Terminal Urbano","DiaSemana":"7","Hora":"08:35"},
		{"LinhaID":"Campo Água Verde","RoteiroInicio":"Bairro Campo Água Verde","RoteiroFim":"Terminal Urbano","DiaSemana":"7","Hora":"09:35"},
		{"LinhaID":"Campo Água Verde","RoteiroInicio":"Bairro Campo Água Verde","RoteiroFim":"Terminal Urbano","DiaSemana":"7","Hora":"10:35"},
		{"LinhaID":"Campo Água Verde","RoteiroInicio":"Bairro Campo Água Verde","RoteiroFim":"Terminal Urbano","DiaSemana":"7","Hora":"11:35"},
		{"LinhaID":"Campo Água Verde","RoteiroInicio":"Bairro Campo Água Verde","RoteiroFim":"Terminal Urbano","DiaSemana":"7","Hora":"12:35"},
		{"LinhaID":"Campo Água Verde","RoteiroInicio":"Bairro Campo Água Verde","RoteiroFim":"Terminal Urbano","DiaSemana":"7","Hora":"13:35"},
		{"LinhaID":"Campo Água Verde","RoteiroInicio":"Bairro Campo Água Verde","RoteiroFim":"Terminal Urbano","DiaSemana":"7","Hora":"14:35"},
		{"LinhaID":"Campo Água Verde","RoteiroInicio":"Bairro Campo Água Verde","RoteiroFim":"Terminal Urbano","DiaSemana":"7","Hora":"15:35"},
		{"LinhaID":"Campo Água Verde","RoteiroInicio":"Bairro Campo Água Verde","RoteiroFim":"Terminal Urbano","DiaSemana":"7","Hora":"16:35"},
		{"LinhaID":"Campo Água Verde","RoteiroInicio":"Bairro Campo Água Verde","RoteiroFim":"Terminal Urbano","DiaSemana":"7","Hora":"17:35"},
		{"LinhaID":"Campo Água Verde","RoteiroInicio":"Bairro Campo Água Verde","RoteiroFim":"Terminal Urbano","DiaSemana":"7","Hora":"18:35"},
		{"LinhaID":"Campo Água Verde","RoteiroInicio":"Terminal Urbano","RoteiroFim":"Bairro Campo Água Verde","DiaSemana":"0, 1","Hora":"07:05"},
		{"LinhaID":"Campo Água Verde","RoteiroInicio":"Terminal Urbano","RoteiroFim":"Bairro Campo Água Verde","DiaSemana":"0, 1","Hora":"09:05"},
		{"LinhaID":"Campo Água Verde","RoteiroInicio":"Terminal Urbano","RoteiroFim":"Bairro Campo Água Verde","DiaSemana":"0, 1","Hora":"13:05"},
		{"LinhaID":"Campo Água Verde","RoteiroInicio":"Terminal Urbano","RoteiroFim":"Bairro Campo Água Verde","DiaSemana":"0, 1","Hora":"16:05"},
		{"LinhaID":"Campo Água Verde","RoteiroInicio":"Terminal Urbano","RoteiroFim":"Bairro Campo Água Verde","DiaSemana":"0, 1","Hora":"17:05"},
		{"LinhaID":"Campo Água Verde","RoteiroInicio":"Bairro Campo Água Verde","RoteiroFim":"Terminal Urbano","DiaSemana":"0, 1","Hora":"09:00"},
		{"LinhaID":"Campo Água Verde","RoteiroInicio":"Bairro Campo Água Verde","RoteiroFim":"Terminal Urbano","DiaSemana":"0, 1","Hora":"10:00"},
		{"LinhaID":"Campo Água Verde","RoteiroInicio":"Bairro Campo Água Verde","RoteiroFim":"Terminal Urbano","DiaSemana":"0, 1","Hora":"15:00"},
		{"LinhaID":"Campo Água Verde","RoteiroInicio":"Bairro Campo Água Verde","RoteiroFim":"Terminal Urbano","DiaSemana":"0, 1","Hora":"16:00"},
		{"LinhaID":"Campo Água Verde","RoteiroInicio":"Bairro Campo Água Verde","RoteiroFim":"Terminal Urbano","DiaSemana":"0, 1","Hora":"17:00"},
		{"LinhaID":"Cohab II","RoteiroInicio":"Terminal Urbano","RoteiroFim":"Bairro Cohab II","DiaSemana":"0, 1","Hora":"06:30"},
		{"LinhaID":"Cohab II","RoteiroInicio":"Terminal Urbano","RoteiroFim":"Bairro Cohab II","DiaSemana":"0, 1","Hora":"07:30"},
		{"LinhaID":"Cohab II","RoteiroInicio":"Terminal Urbano","RoteiroFim":"Bairro Cohab II","DiaSemana":"0, 1","Hora":"08:30"},
		{"LinhaID":"Cohab II","RoteiroInicio":"Terminal Urbano","RoteiroFim":"Bairro Cohab II","DiaSemana":"0, 1","Hora":"09:30"},
		{"LinhaID":"Cohab II","RoteiroInicio":"Terminal Urbano","RoteiroFim":"Bairro Cohab II","DiaSemana":"0, 1","Hora":"10:30"},
		{"LinhaID":"Cohab II","RoteiroInicio":"Terminal Urbano","RoteiroFim":"Bairro Cohab II","DiaSemana":"0, 1","Hora":"11:30"},
		{"LinhaID":"Cohab II","RoteiroInicio":"Terminal Urbano","RoteiroFim":"Bairro Cohab II","DiaSemana":"0, 1","Hora":"12:30"},
		{"LinhaID":"Cohab II","RoteiroInicio":"Terminal Urbano","RoteiroFim":"Bairro Cohab II","DiaSemana":"0, 1","Hora":"13:30"},
		{"LinhaID":"Cohab II","RoteiroInicio":"Terminal Urbano","RoteiroFim":"Bairro Cohab II","DiaSemana":"0, 1","Hora":"14:30"},
		{"LinhaID":"Cohab II","RoteiroInicio":"Terminal Urbano","RoteiroFim":"Bairro Cohab II","DiaSemana":"0, 1","Hora":"15:30"},
		{"LinhaID":"Cohab II","RoteiroInicio":"Terminal Urbano","RoteiroFim":"Bairro Cohab II","DiaSemana":"0, 1","Hora":"16:30"},
		{"LinhaID":"Cohab II","RoteiroInicio":"Terminal Urbano","RoteiroFim":"Bairro Cohab II","DiaSemana":"0, 1","Hora":"17:30"},
		{"LinhaID":"Cohab II","RoteiroInicio":"Terminal Urbano","RoteiroFim":"Bairro Cohab II","DiaSemana":"0, 1","Hora":"18:30"},
		{"LinhaID":"Cohab II","RoteiroInicio":"Terminal Urbano","RoteiroFim":"Bairro Cohab II","DiaSemana":"0, 1","Hora":"19:30"},
		{"LinhaID":"Cohab II","RoteiroInicio":"Terminal Urbano","RoteiroFim":"Bairro Cohab II","DiaSemana":"7","Hora":"06:30"},
		{"LinhaID":"Cohab II","RoteiroInicio":"Terminal Urbano","RoteiroFim":"Bairro Cohab II","DiaSemana":"7","Hora":"07:30"},
		{"LinhaID":"Cohab II","RoteiroInicio":"Terminal Urbano","RoteiroFim":"Bairro Cohab II","DiaSemana":"7","Hora":"08:30"},
		{"LinhaID":"Cohab II","RoteiroInicio":"Terminal Urbano","RoteiroFim":"Bairro Cohab II","DiaSemana":"7","Hora":"09:30"},
		{"LinhaID":"Cohab II","RoteiroInicio":"Terminal Urbano","RoteiroFim":"Bairro Cohab II","DiaSemana":"7","Hora":"10:30"},
		{"LinhaID":"Cohab II","RoteiroInicio":"Terminal Urbano","RoteiroFim":"Bairro Cohab II","DiaSemana":"7","Hora":"11:30"},
		{"LinhaID":"Cohab II","RoteiroInicio":"Terminal Urbano","RoteiroFim":"Bairro Cohab II","DiaSemana":"7","Hora":"12:30"},
		{"LinhaID":"Cohab II","RoteiroInicio":"Terminal Urbano","RoteiroFim":"Bairro Cohab II","DiaSemana":"7","Hora":"13:30"},
		{"LinhaID":"Cohab II","RoteiroInicio":"Terminal Urbano","RoteiroFim":"Bairro Cohab II","DiaSemana":"7","Hora":"14:30"},
		{"LinhaID":"Cohab II","RoteiroInicio":"Terminal Urbano","RoteiroFim":"Bairro Cohab II","DiaSemana":"7","Hora":"15:30"},
		{"LinhaID":"Cohab II","RoteiroInicio":"Terminal Urbano","RoteiroFim":"Bairro Cohab II","DiaSemana":"7","Hora":"16:30"},
		{"LinhaID":"Cohab II","RoteiroInicio":"Terminal Urbano","RoteiroFim":"Bairro Cohab II","DiaSemana":"7","Hora":"17:30"},
		{"LinhaID":"Cohab II","RoteiroInicio":"Terminal Urbano","RoteiroFim":"Bairro Cohab II","DiaSemana":"7","Hora":"18:30"},
		{"LinhaID":"Cohab II","RoteiroInicio":"Terminal Urbano","RoteiroFim":"Bairro Cohab II","DiaSemana":"0, 1","Hora":"09:00"},
		{"LinhaID":"Cohab II","RoteiroInicio":"Terminal Urbano","RoteiroFim":"Bairro Cohab II","DiaSemana":"0, 1","Hora":"10:00"},
		{"LinhaID":"Cohab II","RoteiroInicio":"Terminal Urbano","RoteiroFim":"Bairro Cohab II","DiaSemana":"0, 1","Hora":"15:00"},
		{"LinhaID":"Cohab II","RoteiroInicio":"Terminal Urbano","RoteiroFim":"Bairro Cohab II","DiaSemana":"0, 1","Hora":"16:00"},
		{"LinhaID":"Cohab II","RoteiroInicio":"Terminal Urbano","RoteiroFim":"Bairro Cohab II","DiaSemana":"0, 1","Hora":"17:00"}
  ],
  
  "horaLinhaPontos":[
		{"LinhaID":"Campo Água Verde","RoteiroInicio":"Praça","SentidoLinha":"Bairro Água Verde","PontoID":"Ponto 1","Descrição":"Inicio da linha.","IntervaloMin":"0","IntervaloSeg":"0"},
		{"LinhaID":"Campo Água Verde","RoteiroInicio":"Praça","SentidoLinha":"Bairro Água Verde","PontoID":"Ponto 2","Descrição":"-","IntervaloMin":"1","IntervaloSeg":"42"},
		{"LinhaID":"Campo Água Verde","RoteiroInicio":"Praça","SentidoLinha":"Bairro Água Verde","PontoID":"Ponto 3","Descrição":"-","IntervaloMin":"1","IntervaloSeg":"42"},
		{"LinhaID":"Campo Água Verde","RoteiroInicio":"Praça","SentidoLinha":"Bairro Água Verde","PontoID":"Ponto 4","Descrição":"-","IntervaloMin":"1","IntervaloSeg":"42"},
		{"LinhaID":"Campo Água Verde","RoteiroInicio":"Praça","SentidoLinha":"Bairro Água Verde","PontoID":"Ponto 5","Descrição":"-","IntervaloMin":"1","IntervaloSeg":"42"},
		{"LinhaID":"Campo Água Verde","RoteiroInicio":"Praça","SentidoLinha":"Bairro Água Verde","PontoID":"Ponto 6","Descrição":"-","IntervaloMin":"1","IntervaloSeg":"42"},
		{"LinhaID":"Campo Água Verde","RoteiroInicio":"Praça","SentidoLinha":"Bairro Água Verde","PontoID":"Ponto 7","Descrição":"-","IntervaloMin":"1","IntervaloSeg":"42"},
		{"LinhaID":"Campo Água Verde","RoteiroInicio":"Praça","SentidoLinha":"Bairro Água Verde","PontoID":"Ponto 8","Descrição":"-","IntervaloMin":"1","IntervaloSeg":"42"},
		{"LinhaID":"Campo Água Verde","RoteiroInicio":"Praça","SentidoLinha":"Bairro Água Verde","PontoID":"Ponto 9","Descrição":"-","IntervaloMin":"1","IntervaloSeg":"42"},
		{"LinhaID":"Campo Água Verde","RoteiroInicio":"Praça","SentidoLinha":"Bairro Água Verde","PontoID":"Ponto 10","Descrição":"-","IntervaloMin":"1","IntervaloSeg":"42"},
		{"LinhaID":"Campo Água Verde","RoteiroInicio":"Praça","SentidoLinha":"Bairro Água Verde","PontoID":"Ponto 11","Descrição":"-","IntervaloMin":"1","IntervaloSeg":"42"},
		{"LinhaID":"Campo Água Verde","RoteiroInicio":"Praça","SentidoLinha":"Bairro Água Verde","PontoID":"Ponto 12","Descrição":"-","IntervaloMin":"1","IntervaloSeg":"42"},
		{"LinhaID":"Campo Água Verde","RoteiroInicio":"Praça","SentidoLinha":"Bairro Água Verde","PontoID":"Ponto 13","Descrição":"-","IntervaloMin":"1","IntervaloSeg":"42"},
		{"LinhaID":"Campo Água Verde","RoteiroInicio":"Praça","SentidoLinha":"Bairro Água Verde","PontoID":"Ponto 14","Descrição":"-","IntervaloMin":"1","IntervaloSeg":"42"},
		{"LinhaID":"Campo Água Verde","RoteiroInicio":"Praça","SentidoLinha":"Bairro Água Verde","PontoID":"Ponto 15","Descrição":"-","IntervaloMin":"1","IntervaloSeg":"42"},
		{"LinhaID":"Campo Água Verde","RoteiroInicio":"Praça","SentidoLinha":"Bairro Água Verde","PontoID":"Ponto 16","Descrição":"-","IntervaloMin":"1","IntervaloSeg":"42"},
		{"LinhaID":"Campo Água Verde","RoteiroInicio":"Praça","SentidoLinha":"Bairro Água Verde","PontoID":"Ponto 17","Descrição":"-","IntervaloMin":"1","IntervaloSeg":"42"},
		{"LinhaID":"Campo Água Verde","RoteiroInicio":"Praça","SentidoLinha":"Bairro Água Verde","PontoID":"Ponto 18","Descrição":"-","IntervaloMin":"1","IntervaloSeg":"42"},
		{"LinhaID":"Campo Água Verde","RoteiroInicio":"Praça","SentidoLinha":"Bairro Água Verde","PontoID":"Ponto 19","Descrição":"-","IntervaloMin":"1","IntervaloSeg":"42"},
		{"LinhaID":"Campo Água Verde","RoteiroInicio":"Praça","SentidoLinha":"Bairro Água Verde","PontoID":"Ponto 20","Descrição":"-","IntervaloMin":"1","IntervaloSeg":"42"},
		{"LinhaID":"Campo Água Verde","RoteiroInicio":"Praça","SentidoLinha":"Bairro Água Verde","PontoID":"Ponto 21","Descrição":"-","IntervaloMin":"1","IntervaloSeg":"42"},
		{"LinhaID":"Campo Água Verde","RoteiroInicio":"Praça","SentidoLinha":"Bairro Água Verde","PontoID":"Ponto 22","Descrição":"Último ponto antes do retorno para a praça. ","IntervaloMin":"2","IntervaloSeg":"0"},
		{"LinhaID":"Campo Água Verde","RoteiroInicio":"Praça","SentidoLinha":"Praça Lauro Mueller","PontoID":"Ponto 23","Descrição":"-","IntervaloMin":"2","IntervaloSeg":"0"},
		{"LinhaID":"Campo Água Verde","RoteiroInicio":"Praça","SentidoLinha":"Praça Lauro Mueller","PontoID":"Ponto 24","Descrição":"-","IntervaloMin":"2","IntervaloSeg":"0"},
		{"LinhaID":"Campo Água Verde","RoteiroInicio":"Praça","SentidoLinha":"Praça Lauro Mueller","PontoID":"Ponto 25","Descrição":"-","IntervaloMin":"2","IntervaloSeg":"0"},
		{"LinhaID":"Campo Água Verde","RoteiroInicio":"Praça","SentidoLinha":"Praça Lauro Mueller","PontoID":"Ponto 26","Descrição":"-","IntervaloMin":"2","IntervaloSeg":"0"},
		{"LinhaID":"Campo Água Verde","RoteiroInicio":"Praça","SentidoLinha":"Praça Lauro Mueller","PontoID":"Ponto 27","Descrição":"-","IntervaloMin":"2","IntervaloSeg":"0"},
		{"LinhaID":"Campo Água Verde","RoteiroInicio":"Praça","SentidoLinha":"Praça Lauro Mueller","PontoID":"Ponto 28","Descrição":"-","IntervaloMin":"2","IntervaloSeg":"0"},
		{"LinhaID":"Campo Água Verde","RoteiroInicio":"Praça","SentidoLinha":"Praça Lauro Mueller","PontoID":"Ponto 29","Descrição":"-","IntervaloMin":"3","IntervaloSeg":"0"},
		{"LinhaID":"Campo Água Verde","RoteiroInicio":"Praça","SentidoLinha":"Praça Lauro Mueller","PontoID":"Ponto 30","Descrição":"-","IntervaloMin":"2","IntervaloSeg":"0"},
		{"LinhaID":"Campo Água Verde","RoteiroInicio":"Praça","SentidoLinha":"Praça Lauro Mueller","PontoID":"Ponto 31","Descrição":"-","IntervaloMin":"2","IntervaloSeg":"0"},
		{"LinhaID":"Campo Água Verde","RoteiroInicio":"Praça","SentidoLinha":"Praça Lauro Mueller","PontoID":"Ponto 32","Descrição":"-","IntervaloMin":"2","IntervaloSeg":"0"},
		{"LinhaID":"Campo Água Verde","RoteiroInicio":"Praça","SentidoLinha":"Praça Lauro Mueller","PontoID":"Ponto 33","Descrição":"-","IntervaloMin":"2","IntervaloSeg":"0"},
		{"LinhaID":"Campo Água Verde","RoteiroInicio":"Praça","SentidoLinha":"Praça Lauro Mueller","PontoID":"Ponto 34","Descrição":"-","IntervaloMin":"2","IntervaloSeg":"0"},
		{"LinhaID":"Campo Água Verde","RoteiroInicio":"Praça","SentidoLinha":"Praça Lauro Mueller","PontoID":"Ponto 35","Descrição":"-","IntervaloMin":"2","IntervaloSeg":"0"},
		{"LinhaID":"Campo Água Verde","RoteiroInicio":"Praça","SentidoLinha":"Praça Lauro Mueller","PontoID":"Ponto 1","Descrição":"Ponto final. ","IntervaloMin":"2","IntervaloSeg":"0"},
		{"LinhaID":"Aparecida","RoteiroInicio":"Praça","SentidoLinha":"Bairro Piedade","PontoID":"Ponto 1","Descrição":"Ponto inicial.","IntervaloMin":"1","IntervaloSeg":"52"},
		{"LinhaID":"Aparecida","RoteiroInicio":"Praça","SentidoLinha":"Bairro Piedade","PontoID":"Ponto 36","Descrição":"-","IntervaloMin":"1","IntervaloSeg":"52"},
		{"LinhaID":"Aparecida","RoteiroInicio":"Praça","SentidoLinha":"Bairro Piedade","PontoID":"Ponto 37","Descrição":"-","IntervaloMin":"1","IntervaloSeg":"52"},
		{"LinhaID":"Aparecida","RoteiroInicio":"Praça","SentidoLinha":"Bairro Piedade","PontoID":"Ponto 38","Descrição":"-","IntervaloMin":"1","IntervaloSeg":"52"},
		{"LinhaID":"Aparecida","RoteiroInicio":"Praça","SentidoLinha":"Bairro Piedade","PontoID":"Ponto 39","Descrição":"-","IntervaloMin":"1","IntervaloSeg":"52"},
		{"LinhaID":"Aparecida","RoteiroInicio":"Praça","SentidoLinha":"Bairro Piedade","PontoID":"Ponto 40","Descrição":"-","IntervaloMin":"1","IntervaloSeg":"52"},
		{"LinhaID":"Aparecida","RoteiroInicio":"Praça","SentidoLinha":"Bairro Piedade","PontoID":"Ponto 41","Descrição":"-","IntervaloMin":"1","IntervaloSeg":"52"},
		{"LinhaID":"Aparecida","RoteiroInicio":"Praça","SentidoLinha":"Bairro Piedade","PontoID":"Ponto 42","Descrição":"-","IntervaloMin":"1","IntervaloSeg":"52"},
		{"LinhaID":"Aparecida","RoteiroInicio":"Praça","SentidoLinha":"Bairro Piedade","PontoID":"Ponto 43","Descrição":"-","IntervaloMin":"1","IntervaloSeg":"52"},
		{"LinhaID":"Aparecida","RoteiroInicio":"Praça","SentidoLinha":"Centro","PontoID":"Ponto 44","Descrição":"-","IntervaloMin":"1","IntervaloSeg":"52"},
		{"LinhaID":"Aparecida","RoteiroInicio":"Praça","SentidoLinha":"Centro","PontoID":"Ponto 45","Descrição":"-","IntervaloMin":"1","IntervaloSeg":"52"},
		{"LinhaID":"Aparecida","RoteiroInicio":"Praça","SentidoLinha":"Centro","PontoID":"Ponto 46","Descrição":"-","IntervaloMin":"1","IntervaloSeg":"52"},
		{"LinhaID":"Aparecida","RoteiroInicio":"Praça","SentidoLinha":"Centro","PontoID":"Ponto 47","Descrição":"-","IntervaloMin":"1","IntervaloSeg":"52"},
		{"LinhaID":"Aparecida","RoteiroInicio":"Praça","SentidoLinha":"Centro","PontoID":"Ponto 48","Descrição":"-","IntervaloMin":"1","IntervaloSeg":"52"},
		{"LinhaID":"Aparecida","RoteiroInicio":"Praça","SentidoLinha":"Centro","PontoID":"Ponto 49","Descrição":"-","IntervaloMin":"1","IntervaloSeg":"52"},
		{"LinhaID":"Aparecida","RoteiroInicio":"Praça","SentidoLinha":"Centro","PontoID":"Ponto 50","Descrição":"-","IntervaloMin":"1","IntervaloSeg":"52"},
		{"LinhaID":"Aparecida","RoteiroInicio":"Praça","SentidoLinha":"Centro","PontoID":"Ponto 51","Descrição":"-","IntervaloMin":"1","IntervaloSeg":"52"},
		{"LinhaID":"Aparecida","RoteiroInicio":"Praça","SentidoLinha":"Centro","PontoID":"Ponto 52","Descrição":"-","IntervaloMin":"1","IntervaloSeg":"52"},
		{"LinhaID":"Aparecida","RoteiroInicio":"Praça","SentidoLinha":"Centro","PontoID":"Ponto 53","Descrição":"-","IntervaloMin":"1","IntervaloSeg":"52"},
		{"LinhaID":"Aparecida","RoteiroInicio":"Praça","SentidoLinha":"Bairro Jardim Esperança","PontoID":"Ponto 54","Descrição":"-","IntervaloMin":"1","IntervaloSeg":"52"},
		{"LinhaID":"Aparecida","RoteiroInicio":"Praça","SentidoLinha":"Bairro Jardim Esperança","PontoID":"Ponto 55","Descrição":"-","IntervaloMin":"1","IntervaloSeg":"52"},
		{"LinhaID":"Aparecida","RoteiroInicio":"Praça","SentidoLinha":"Bairro Jardim Esperança","PontoID":"Ponto 56","Descrição":"-","IntervaloMin":"1","IntervaloSeg":"52"},
		{"LinhaID":"Aparecida","RoteiroInicio":"Praça","SentidoLinha":"Bairro Jardim Esperança","PontoID":"Ponto 57","Descrição":"-","IntervaloMin":"1","IntervaloSeg":"52"},
		{"LinhaID":"Aparecida","RoteiroInicio":"Praça","SentidoLinha":"Bairro Jardim Esperança","PontoID":"Ponto 58","Descrição":"-","IntervaloMin":"1","IntervaloSeg":"52"},
		{"LinhaID":"Aparecida","RoteiroInicio":"Praça","SentidoLinha":"Bairro Jardim Esperança","PontoID":"Ponto 59","Descrição":"-","IntervaloMin":"1","IntervaloSeg":"52"},
		{"LinhaID":"Aparecida","RoteiroInicio":"Praça","SentidoLinha":"Bairro Jardim Esperança","PontoID":"Ponto 60","Descrição":"-","IntervaloMin":"1","IntervaloSeg":"52"},
		{"LinhaID":"Aparecida","RoteiroInicio":"Praça","SentidoLinha":"Bairro Jardim Esperança","PontoID":"Ponto 61","Descrição":"-","IntervaloMin":"1","IntervaloSeg":"52"},
		{"LinhaID":"Aparecida","RoteiroInicio":"Praça","SentidoLinha":"Bairro Jardim Esperança","PontoID":"Ponto 62","Descrição":"-","IntervaloMin":"1","IntervaloSeg":"52"},
		{"LinhaID":"Aparecida","RoteiroInicio":"Praça","SentidoLinha":"Centro","PontoID":"Ponto 63","Descrição":"-","IntervaloMin":"1","IntervaloSeg":"52"},
		{"LinhaID":"Aparecida","RoteiroInicio":"Praça","SentidoLinha":"Centro","PontoID":"Ponto 64","Descrição":"-","IntervaloMin":"1","IntervaloSeg":"52"},
		{"LinhaID":"Aparecida","RoteiroInicio":"Praça","SentidoLinha":"Centro","PontoID":"Ponto 65","Descrição":"-","IntervaloMin":"1","IntervaloSeg":"52"},
		{"LinhaID":"Aparecida","RoteiroInicio":"Praça","SentidoLinha":"Centro","PontoID":"Ponto 66","Descrição":"-","IntervaloMin":"1","IntervaloSeg":"52"},
		{"LinhaID":"Aparecida","RoteiroInicio":"Praça","SentidoLinha":"Centro","PontoID":"Ponto 67","Descrição":"Ponto final. ","IntervaloMin":"1","IntervaloSeg":"52"},
		{"LinhaID":"Cohab I, II","RoteiroInicio":"Praça","SentidoLinha":"Sentido Fricassa","PontoID":"Ponto 1","Descrição":"Ponto incial. ","IntervaloMin":"1","IntervaloSeg":"37"},
		{"LinhaID":"Cohab I, II","RoteiroInicio":"Praça","SentidoLinha":"Sentido Fricassa","PontoID":"Ponto 68","Descrição":"-","IntervaloMin":"1","IntervaloSeg":"37"},
		{"LinhaID":"Cohab I, II","RoteiroInicio":"Praça","SentidoLinha":"Sentido Fricassa","PontoID":"Ponto 69","Descrição":"-","IntervaloMin":"1","IntervaloSeg":"37"},
		{"LinhaID":"Cohab I, II","RoteiroInicio":"Praça","SentidoLinha":"Sentido Fricassa","PontoID":"Ponto 70","Descrição":"-","IntervaloMin":"1","IntervaloSeg":"37"},
		{"LinhaID":"Cohab I, II","RoteiroInicio":"Praça","SentidoLinha":"Sentido Fricassa","PontoID":"Ponto 71","Descrição":"-","IntervaloMin":"1","IntervaloSeg":"37"},
		{"LinhaID":"Cohab I, II","RoteiroInicio":"Praça","SentidoLinha":"Sentido Fricassa","PontoID":"Ponto 72","Descrição":"-","IntervaloMin":"1","IntervaloSeg":"37"},
		{"LinhaID":"Cohab I, II","RoteiroInicio":"Praça","SentidoLinha":"Sentido Fricassa","PontoID":"Ponto 73","Descrição":"-","IntervaloMin":"1","IntervaloSeg":"37"},
		{"LinhaID":"Cohab I, II","RoteiroInicio":"Praça","SentidoLinha":"Sentido Fricassa","PontoID":"Ponto 74","Descrição":"-","IntervaloMin":"1","IntervaloSeg":"37"},
		{"LinhaID":"Cohab I, II","RoteiroInicio":"Praça","SentidoLinha":"Sentido Fricassa","PontoID":"Ponto 75","Descrição":"-","IntervaloMin":"1","IntervaloSeg":"37"},
		{"LinhaID":"Cohab I, II","RoteiroInicio":"Praça","SentidoLinha":"Sentido Fricassa","PontoID":"Ponto 76","Descrição":"-","IntervaloMin":"1","IntervaloSeg":"37"},
		{"LinhaID":"Cohab I, II","RoteiroInicio":"Praça","SentidoLinha":"Sentido Fricassa","PontoID":"Ponto 77","Descrição":"-","IntervaloMin":"1","IntervaloSeg":"37"},
		{"LinhaID":"Cohab I, II","RoteiroInicio":"Praça","SentidoLinha":"Centro ","PontoID":"Ponto 78","Descrição":"-","IntervaloMin":"1","IntervaloSeg":"37"},
		{"LinhaID":"Cohab I, II","RoteiroInicio":"Praça","SentidoLinha":"Centro ","PontoID":"Ponto 79","Descrição":"-","IntervaloMin":"1","IntervaloSeg":"37"},
		{"LinhaID":"Cohab I, II","RoteiroInicio":"Praça","SentidoLinha":"Centro ","PontoID":"Ponto 80","Descrição":"-","IntervaloMin":"1","IntervaloSeg":"37"},
		{"LinhaID":"Cohab I, II","RoteiroInicio":"Praça","SentidoLinha":"Centro ","PontoID":"Ponto 81","Descrição":"-","IntervaloMin":"1","IntervaloSeg":"37"},
		{"LinhaID":"Cohab I, II","RoteiroInicio":"Praça","SentidoLinha":"Centro ","PontoID":"Ponto 82","Descrição":"-","IntervaloMin":"1","IntervaloSeg":"37"},
		{"LinhaID":"Cohab I, II","RoteiroInicio":"Praça","SentidoLinha":"Centro ","PontoID":"Ponto 64","Descrição":"-","IntervaloMin":"1","IntervaloSeg":"37"},
		{"LinhaID":"Cohab I, II","RoteiroInicio":"Praça","SentidoLinha":"Centro ","PontoID":"Ponto 83","Descrição":"-","IntervaloMin":"1","IntervaloSeg":"37"},
		{"LinhaID":"Cohab I, II","RoteiroInicio":"Praça","SentidoLinha":"Centro ","PontoID":"Ponto 84","Descrição":"-","IntervaloMin":"1","IntervaloSeg":"37"},
		{"LinhaID":"Cohab I, II","RoteiroInicio":"Praça","SentidoLinha":"Centro ","PontoID":"Ponto 36","Descrição":"-","IntervaloMin":"1","IntervaloSeg":"37"},
		{"LinhaID":"Cohab I, II","RoteiroInicio":"Praça","SentidoLinha":"Bairro Água Verde","PontoID":"Ponto 85","Descrição":"-","IntervaloMin":"1","IntervaloSeg":"37"},
		{"LinhaID":"Cohab I, II","RoteiroInicio":"Praça","SentidoLinha":"Bairro Água Verde","PontoID":"Ponto 86","Descrição":"-","IntervaloMin":"1","IntervaloSeg":"37"},
		{"LinhaID":"Cohab I, II","RoteiroInicio":"Praça","SentidoLinha":"Bairro Água Verde","PontoID":"Ponto 87","Descrição":"-","IntervaloMin":"1","IntervaloSeg":"37"},
		{"LinhaID":"Cohab I, II","RoteiroInicio":"Praça","SentidoLinha":"Bairro Água Verde","PontoID":"Ponto 88","Descrição":"-","IntervaloMin":"1","IntervaloSeg":"37"},
		{"LinhaID":"Cohab I, II","RoteiroInicio":"Praça","SentidoLinha":"Bairro Água Verde","PontoID":"Ponto 89","Descrição":"-","IntervaloMin":"1","IntervaloSeg":"37"},
		{"LinhaID":"Cohab I, II","RoteiroInicio":"Praça","SentidoLinha":"Bairro Água Verde","PontoID":"Ponto 90","Descrição":"-","IntervaloMin":"1","IntervaloSeg":"37"},
		{"LinhaID":"Cohab I, II","RoteiroInicio":"Praça","SentidoLinha":"Bairro Água Verde","PontoID":"Ponto 91","Descrição":"-","IntervaloMin":"1","IntervaloSeg":"37"},
		{"LinhaID":"Cohab I, II","RoteiroInicio":"Praça","SentidoLinha":"Bairro Água Verde","PontoID":"Ponto 92","Descrição":"-","IntervaloMin":"1","IntervaloSeg":"37"},
		{"LinhaID":"Cohab I, II","RoteiroInicio":"Praça","SentidoLinha":"Centro","PontoID":"Ponto 93","Descrição":"-","IntervaloMin":"1","IntervaloSeg":"37"},
		{"LinhaID":"Cohab I, II","RoteiroInicio":"Praça","SentidoLinha":"Centro","PontoID":"Ponto 94","Descrição":"-","IntervaloMin":"1","IntervaloSeg":"37"},
		{"LinhaID":"Cohab I, II","RoteiroInicio":"Praça","SentidoLinha":"Centro","PontoID":"Ponto 95","Descrição":"-","IntervaloMin":"1","IntervaloSeg":"37"},
		{"LinhaID":"Cohab I, II","RoteiroInicio":"Praça","SentidoLinha":"Centro","PontoID":"Ponto 96","Descrição":"-","IntervaloMin":"1","IntervaloSeg":"37"},
		{"LinhaID":"Cohab I, II","RoteiroInicio":"Praça","SentidoLinha":"Centro","PontoID":"Ponto 97","Descrição":"-","IntervaloMin":"1","IntervaloSeg":"37"},
		{"LinhaID":"Cohab I, II","RoteiroInicio":"Praça","SentidoLinha":"Centro","PontoID":"Ponto 98","Descrição":"-","IntervaloMin":"1","IntervaloSeg":"37"},
		{"LinhaID":"Cohab I, II","RoteiroInicio":"Praça","SentidoLinha":"Centro","PontoID":"Ponto 99","Descrição":"-","IntervaloMin":"1","IntervaloSeg":"37"},
		{"LinhaID":"Cohab I, II","RoteiroInicio":"Praça","SentidoLinha":"Centro","PontoID":"Ponto 100","Descrição":"-","IntervaloMin":"1","IntervaloSeg":"37"},
		{"LinhaID":"Cohab I, II","RoteiroInicio":"Praça","SentidoLinha":"Centro","PontoID":"Ponto 53","Descrição":"-","IntervaloMin":"1","IntervaloSeg":"37"},
		{"LinhaID":"Cohab I, II","RoteiroInicio":"Praça","SentidoLinha":"Centro","PontoID":"Ponto 1","Descrição":"Ponto final. ","IntervaloMin":"1","IntervaloSeg":"37"}
  ]
}